{"sku": "D-13300N", "dc": "SF", "weekly": [{"week_start": "2023-01-16", "MM": 0.0, "AM": 56.0, "HF": 0.0}, {"week_start": "2023-01-23", "MM": 1.0, "AM": 135.0, "HF": 0.0}, {"week_start": "2023-01-30", "MM": 1.0, "AM": 130.0, "HF": 0.0}, {"week_start": "2023-02-06", "MM": 1.0, "AM": 146.0, "HF": 0.0}, {"week_start": "2023-02-13", "MM": 0.0, "AM": 76.0, "HF": 0.0}, {"week_start": "2023-02-20", "MM": 0.0, "AM": 6.0, "HF": 0.0}, {"week_start": "2023-02-27", "MM": 3.0, "AM": 140.0, "HF": 0.0}, {"week_start": "2023-03-06", "MM": 1.0, "AM": 74.0, "HF": 0.0}, {"week_start": "2023-03-13", "MM": 0.0, "AM": 72.0, "HF": 0.0}, {"week_start": "2023-03-20", "MM": 1.0, "AM": 26.0, "HF": 0.0}, {"week_start": "2023-03-27", "MM": 1.0, "AM": 16.0, "HF": 0.0}, {"week_start": "2023-04-03", "MM": 0.0, "AM": 49.0, "HF": 0.0}, {"week_start": "2023-04-10", "MM": 0.0, "AM": 120.0, "HF": 0.0}, {"week_start": "2023-04-17", "MM": 4.0, "AM": 70.0, "HF": 0.0}, {"week_start": "2023-04-24", "MM": 1.0, "AM": 62.0, "HF": 0.0}, {"week_start": "2023-05-01", "MM": 0.0, "AM": 156.0, "HF": 0.0}, {"week_start": "2023-05-08", "MM": 2.0, "AM": 97.0, "HF": 0.0}, {"week_start": "2023-05-15", "MM": 0.0, "AM": 40.0, "HF": 0.0}, {"week_start": "2023-05-22", "MM": 0.0, "AM": 82.0, "HF": 0.0}, {"week_start": "2023-05-29", "MM": 0.0, "AM": 56.0, "HF": 0.0}, {"week_start": "2023-06-05", "MM": 0.0, "AM": 12.0, "HF": 0.0}, {"week_start": "2023-06-12", "MM": 0.0, "AM": 12.0, "HF": 0.0}, {"week_start": "2023-06-19", "MM": 0.0, "AM": 60.0, "HF": 0.0}, {"week_start": "2023-06-26", "MM": 0.0, "AM": 66.0, "HF": 0.0}, {"week_start": "2023-07-10", "MM": 0.0, "AM": 12.0, "HF": 0.0}, {"week_start": "2023-07-24", "MM": 0.0, "AM": 12.0, "HF": 0.0}, {"week_start": "2023-07-31", "MM": 0.0, "AM": 53.0, "HF": 0.0}, {"week_start": "2023-08-07", "MM": 0.0, "AM": 110.0, "HF": 0.0}, {"week_start": "2023-08-21", "MM": 0.0, "AM": 30.0, "HF": 0.0}, {"week_start": "2023-08-28", "MM": 3.0, "AM": 30.0, "HF": 0.0}, {"week_start": "2023-09-11", "MM": 0.0, "AM": 12.0, "HF": 0.0}, {"week_start": "2023-09-18", "MM": 0.0, "AM": 6.0, "HF": 0.0}, {"week_start": "2023-10-02", "MM": 0.0, "AM": 60.0, "HF": 0.0}, {"week_start": "2023-10-09", "MM": 0.0, "AM": 15.0, "HF": 0.0}, {"week_start": "2023-10-16", "MM": 0.0, "AM": 36.0, "HF": 0.0}, {"week_start": "2024-04-29", "MM": 2.0, "AM": 0.0, "HF": 0.0}], "top_customers": [{"custnmbr": "SBIGT2A", "name": "SBIGT2A", "share_pct": 23.88888888888889, "qty": 129.0}, {"custnmbr": "SPACI2D", "name": "SPACI2D", "share_pct": 22.22222222222222, "qty": 120.0}, {"custnmbr": "SSARI2A", "name": "SSARI2A", "share_pct": 22.22222222222222, "qty": 120.0}, {"custnmbr": "SWING8F", "name": "SWING8F", "share_pct": 16.666666666666664, "qty": 90.0}, {"custnmbr": "SMARI1D", "name": "SMARI1D", "share_pct": 15.0, "qty": 81.0}]}