{"sku": "D-15100N", "dc": "SF", "series": [{"week_start": "2023-04-03", "on_hand_est": null, "reorder_point_mean": 2841.224403088214, "reorder_point_p90": 4551.281545945356, "run_rate_mean": 180.85714285714286, "run_rate_p90": 312.4, "alert_fired_mean": true, "alert_fired_p90": true, "fresh_stockout": false, "weeks_until_stockout": null}, {"week_start": "2023-05-01", "on_hand_est": null, "reorder_point_mean": 2588.916637573486, "reorder_point_p90": 4412.462092118941, "run_rate_mean": 167.72727272727272, "run_rate_p90": 308.0, "alert_fired_mean": true, "alert_fired_p90": true, "fresh_stockout": false, "weeks_until_stockout": null}, {"week_start": "2023-05-29", "on_hand_est": null, "reorder_point_mean": 2349.1300920263316, "reorder_point_p90": 3884.863425359664, "run_rate_mean": 151.86666666666667, "run_rate_p90": 269.99999999999994, "alert_fired_mean": true, "alert_fired_p90": true, "fresh_stockout": false, "weeks_until_stockout": null}, {"week_start": "2023-06-26", "on_hand_est": null, "reorder_point_mean": 2349.1300920263316, "reorder_point_p90": 3884.863425359664, "run_rate_mean": 151.86666666666667, "run_rate_p90": 269.99999999999994, "alert_fired_mean": true, "alert_fired_p90": true, "fresh_stockout": false, "weeks_until_stockout": null}, {"week_start": "2023-07-24", "on_hand_est": null, "reorder_point_mean": 2349.1300920263316, "reorder_point_p90": 3884.863425359664, "run_rate_mean": 151.86666666666667, "run_rate_p90": 269.99999999999994, "alert_fired_mean": true, "alert_fired_p90": true, "fresh_stockout": false, "weeks_until_stockout": null}, {"week_start": "2023-08-21", "on_hand_est": null, "reorder_point_mean": 2253.8143292067534, "reorder_point_p90": 3787.8143292067534, "run_rate_mean": 142.5, "run_rate_p90": 260.5, "alert_fired_mean": true, "alert_fired_p90": true, "fresh_stockout": false, "weeks_until_stockout": null}, {"week_start": "2023-09-18", "on_hand_est": null, "reorder_point_mean": 2253.8143292067534, "reorder_point_p90": 3787.8143292067534, "run_rate_mean": 142.5, "run_rate_p90": 260.5, "alert_fired_mean": true, "alert_fired_p90": true, "fresh_stockout": false, "weeks_until_stockout": null}, {"week_start": "2023-10-16", "on_hand_est": null, "reorder_point_mean": 2253.8143292067534, "reorder_point_p90": 3787.8143292067534, "run_rate_mean": 142.5, "run_rate_p90": 260.5, "alert_fired_mean": true, "alert_fired_p90": true, "fresh_stockout": false, "weeks_until_stockout": null}, {"week_start": "2023-11-13", "on_hand_est": null, "reorder_point_mean": 2253.8143292067534, "reorder_point_p90": 3787.8143292067534, "run_rate_mean": 142.5, "run_rate_p90": 260.5, "alert_fired_mean": true, "alert_fired_p90": true, "fresh_stockout": false, "weeks_until_stockout": null}, {"week_start": "2023-12-11", "on_hand_est": null, "reorder_point_mean": 2253.8143292067534, "reorder_point_p90": 3787.8143292067534, "run_rate_mean": 142.5, "run_rate_p90": 260.5, "alert_fired_mean": true, "alert_fired_p90": true, "fresh_stockout": false, "weeks_until_stockout": null}, {"week_start": "2024-01-08", "on_hand_est": null, "reorder_point_mean": 2253.8143292067534, "reorder_point_p90": 3787.8143292067534, "run_rate_mean": 142.5, "run_rate_p90": 260.5, "alert_fired_mean": true, "alert_fired_p90": true, "fresh_stockout": false, "weeks_until_stockout": null}, {"week_start": "2024-02-05", "on_hand_est": null, "reorder_point_mean": 2253.8143292067534, "reorder_point_p90": 3787.8143292067534, "run_rate_mean": 142.5, "run_rate_p90": 260.5, "alert_fired_mean": true, "alert_fired_p90": true, "fresh_stockout": false, "weeks_until_stockout": null}, {"week_start": "2024-03-04", "on_hand_est": null, "reorder_point_mean": 2253.8143292067534, "reorder_point_p90": 3787.8143292067534, "run_rate_mean": 142.5, "run_rate_p90": 260.5, "alert_fired_mean": true, "alert_fired_p90": true, "fresh_stockout": false, "weeks_until_stockout": null}, {"week_start": "2024-04-01", "on_hand_est": null, "reorder_point_mean": 2253.8143292067534, "reorder_point_p90": 3787.8143292067534, "run_rate_mean": 142.5, "run_rate_p90": 260.5, "alert_fired_mean": true, "alert_fired_p90": true, "fresh_stockout": false, "weeks_until_stockout": null}, {"week_start": "2024-04-29", "on_hand_est": null, "reorder_point_mean": 2253.8143292067534, "reorder_point_p90": 3787.8143292067534, "run_rate_mean": 142.5, "run_rate_p90": 260.5, "alert_fired_mean": true, "alert_fired_p90": true, "fresh_stockout": false, "weeks_until_stockout": null}, {"week_start": "2024-05-27", "on_hand_est": null, "reorder_point_mean": 2253.8143292067534, "reorder_point_p90": 3787.8143292067534, "run_rate_mean": 142.5, "run_rate_p90": 260.5, "alert_fired_mean": true, "alert_fired_p90": true, "fresh_stockout": false, "weeks_until_stockout": null}, {"week_start": "2024-06-24", "on_hand_est": null, "reorder_point_mean": 2253.8143292067534, "reorder_point_p90": 3787.8143292067534, "run_rate_mean": 142.5, "run_rate_p90": 260.5, "alert_fired_mean": true, "alert_fired_p90": true, "fresh_stockout": false, "weeks_until_stockout": null}, {"week_start": "2024-07-22", "on_hand_est": null, "reorder_point_mean": 2253.8143292067534, "reorder_point_p90": 3787.8143292067534, "run_rate_mean": 142.5, "run_rate_p90": 260.5, "alert_fired_mean": true, "alert_fired_p90": true, "fresh_stockout": false, "weeks_until_stockout": null}, {"week_start": "2024-08-19", "on_hand_est": null, "reorder_point_mean": 2253.8143292067534, "reorder_point_p90": 3787.8143292067534, "run_rate_mean": 142.5, "run_rate_p90": 260.5, "alert_fired_mean": true, "alert_fired_p90": true, "fresh_stockout": false, "weeks_until_stockout": null}, {"week_start": "2024-09-16", "on_hand_est": null, "reorder_point_mean": 2253.8143292067534, "reorder_point_p90": 3787.8143292067534, "run_rate_mean": 142.5, "run_rate_p90": 260.5, "alert_fired_mean": true, "alert_fired_p90": true, "fresh_stockout": false, "weeks_until_stockout": null}, {"week_start": "2024-10-14", "on_hand_est": null, "reorder_point_mean": 2253.8143292067534, "reorder_point_p90": 3787.8143292067534, "run_rate_mean": 142.5, "run_rate_p90": 260.5, "alert_fired_mean": true, "alert_fired_p90": true, "fresh_stockout": false, "weeks_until_stockout": null}, {"week_start": "2024-11-11", "on_hand_est": null, "reorder_point_mean": 2253.8143292067534, "reorder_point_p90": 3787.8143292067534, "run_rate_mean": 142.5, "run_rate_p90": 260.5, "alert_fired_mean": true, "alert_fired_p90": true, "fresh_stockout": false, "weeks_until_stockout": null}, {"week_start": "2024-12-09", "on_hand_est": null, "reorder_point_mean": 2253.8143292067534, "reorder_point_p90": 3787.8143292067534, "run_rate_mean": 142.5, "run_rate_p90": 260.5, "alert_fired_mean": true, "alert_fired_p90": true, "fresh_stockout": false, "weeks_until_stockout": null}, {"week_start": "2025-01-06", "on_hand_est": null, "reorder_point_mean": 2253.8143292067534, "reorder_point_p90": 3787.8143292067534, "run_rate_mean": 142.5, "run_rate_p90": 260.5, "alert_fired_mean": true, "alert_fired_p90": true, "fresh_stockout": false, "weeks_until_stockout": null}, {"week_start": "2025-02-03", "on_hand_est": null, "reorder_point_mean": 2253.8143292067534, "reorder_point_p90": 3787.8143292067534, "run_rate_mean": 142.5, "run_rate_p90": 260.5, "alert_fired_mean": true, "alert_fired_p90": true, "fresh_stockout": false, "weeks_until_stockout": null}, {"week_start": "2025-03-03", "on_hand_est": null, "reorder_point_mean": 2253.8143292067534, "reorder_point_p90": 3787.8143292067534, "run_rate_mean": 142.5, "run_rate_p90": 260.5, "alert_fired_mean": true, "alert_fired_p90": true, "fresh_stockout": false, "weeks_until_stockout": null}, {"week_start": "2025-03-31", "on_hand_est": null, "reorder_point_mean": 2253.8143292067534, "reorder_point_p90": 3787.8143292067534, "run_rate_mean": 142.5, "run_rate_p90": 260.5, "alert_fired_mean": true, "alert_fired_p90": true, "fresh_stockout": false, "weeks_until_stockout": null}, {"week_start": "2025-04-28", "on_hand_est": null, "reorder_point_mean": 2253.8143292067534, "reorder_point_p90": 3787.8143292067534, "run_rate_mean": 142.5, "run_rate_p90": 260.5, "alert_fired_mean": true, "alert_fired_p90": true, "fresh_stockout": false, "weeks_until_stockout": null}, {"week_start": "2025-05-26", "on_hand_est": null, "reorder_point_mean": 2253.8143292067534, "reorder_point_p90": 3787.8143292067534, "run_rate_mean": 142.5, "run_rate_p90": 260.5, "alert_fired_mean": true, "alert_fired_p90": true, "fresh_stockout": false, "weeks_until_stockout": null}, {"week_start": "2025-06-23", "on_hand_est": null, "reorder_point_mean": 2253.8143292067534, "reorder_point_p90": 3787.8143292067534, "run_rate_mean": 142.5, "run_rate_p90": 260.5, "alert_fired_mean": true, "alert_fired_p90": true, "fresh_stockout": false, "weeks_until_stockout": null}, {"week_start": "2025-07-21", "on_hand_est": null, "reorder_point_mean": 2253.8143292067534, "reorder_point_p90": 3787.8143292067534, "run_rate_mean": 142.5, "run_rate_p90": 260.5, "alert_fired_mean": true, "alert_fired_p90": true, "fresh_stockout": false, "weeks_until_stockout": null}, {"week_start": "2025-08-18", "on_hand_est": null, "reorder_point_mean": 2253.8143292067534, "reorder_point_p90": 3787.8143292067534, "run_rate_mean": 142.5, "run_rate_p90": 260.5, "alert_fired_mean": true, "alert_fired_p90": true, "fresh_stockout": false, "weeks_until_stockout": null}, {"week_start": "2025-09-15", "on_hand_est": null, "reorder_point_mean": 2253.8143292067534, "reorder_point_p90": 3787.8143292067534, "run_rate_mean": 142.5, "run_rate_p90": 260.5, "alert_fired_mean": true, "alert_fired_p90": true, "fresh_stockout": false, "weeks_until_stockout": null}, {"week_start": "2025-10-13", "on_hand_est": null, "reorder_point_mean": 2253.8143292067534, "reorder_point_p90": 3787.8143292067534, "run_rate_mean": 142.5, "run_rate_p90": 260.5, "alert_fired_mean": true, "alert_fired_p90": true, "fresh_stockout": false, "weeks_until_stockout": null}], "today": {"reorder_flag": true, "confidence": "low", "on_hand": null, "available": null, "reorder_point": 2369.819252493081, "run_rate_wk": 142.5, "lead_time_wk": 13.0, "lead_time_source": "default", "suggested_qty": 2939.819252493081, "suggested_cases": null, "weeks_of_cover": null, "safety_stock": 517.3192524930807, "std_wk": 86.9566942027275, "n_clean_weeks": 16}, "metadata": {"sku_desc": "", "case_pack": null, "vendor": "", "country": ""}}