{"sku": "D-15206", "dc": "LA", "series": [{"week_start": "2023-08-21", "actual": 40006.0, "mean_followed": 40004.0, "p90_followed": 40004.0}, {"week_start": "2023-08-28", "actual": 40004.0, "mean_followed": 37442.0, "p90_followed": 37442.0}, {"week_start": "2023-09-04", "actual": 37442.0, "mean_followed": 37442.0, "p90_followed": 37442.0}, {"week_start": "2023-09-11", "actual": 37442.0, "mean_followed": 37317.0, "p90_followed": 37317.0}, {"week_start": "2023-09-18", "actual": 37317.0, "mean_followed": 37251.0, "p90_followed": 37251.0}, {"week_start": "2023-09-25", "actual": 37251.0, "mean_followed": 37215.0, "p90_followed": 37215.0}, {"week_start": "2023-10-02", "actual": 37215.0, "mean_followed": 36615.0, "p90_followed": 36615.0}, {"week_start": "2023-10-09", "actual": 36615.0, "mean_followed": 36609.0, "p90_followed": 36609.0}, {"week_start": "2023-10-16", "actual": 38241.0, "mean_followed": 36609.0, "p90_followed": 36609.0}, {"week_start": "2023-10-23", "actual": 38241.0, "mean_followed": 36327.0, "p90_followed": 36327.0}, {"week_start": "2023-10-30", "actual": 37959.0, "mean_followed": 36027.0, "p90_followed": 36027.0}, {"week_start": "2023-11-06", "actual": 37659.0, "mean_followed": 35958.0, "p90_followed": 35958.0}, {"week_start": "2023-11-13", "actual": 40094.0, "mean_followed": 35953.0, "p90_followed": 35953.0}, {"week_start": "2023-11-20", "actual": 40089.0, "mean_followed": 35904.0, "p90_followed": 35904.0}, {"week_start": "2023-11-27", "actual": 40040.0, "mean_followed": 35880.0, "p90_followed": 35880.0}, {"week_start": "2023-12-04", "actual": 40016.0, "mean_followed": 35742.0, "p90_followed": 35742.0}, {"week_start": "2023-12-11", "actual": 39878.0, "mean_followed": 35712.0, "p90_followed": 35712.0}, {"week_start": "2023-12-18", "actual": 39848.0, "mean_followed": 35478.0, "p90_followed": 35478.0}, {"week_start": "2023-12-25", "actual": 39614.0, "mean_followed": 34614.0, "p90_followed": 34614.0}, {"week_start": "2024-01-01", "actual": 38750.0, "mean_followed": 34566.0, "p90_followed": 34566.0}, {"week_start": "2024-01-08", "actual": 38702.0, "mean_followed": 34032.0, "p90_followed": 34032.0}, {"week_start": "2024-01-15", "actual": 38168.0, "mean_followed": 33936.0, "p90_followed": 33936.0}, {"week_start": "2024-01-22", "actual": 38072.0, "mean_followed": 33804.0, "p90_followed": 33804.0}, {"week_start": "2024-01-29", "actual": 37940.0, "mean_followed": 33774.0, "p90_followed": 33774.0}, {"week_start": "2024-02-05", "actual": 37910.0, "mean_followed": 31896.0, "p90_followed": 31896.0}, {"week_start": "2024-02-12", "actual": 36032.0, "mean_followed": 31722.0, "p90_followed": 31722.0}, {"week_start": "2024-02-19", "actual": 35858.0, "mean_followed": 31656.0, "p90_followed": 31656.0}, {"week_start": "2024-02-26", "actual": 35792.0, "mean_followed": 31512.0, "p90_followed": 31512.0}, {"week_start": "2024-03-04", "actual": 33200.0, "mean_followed": 30756.0, "p90_followed": 30756.0}, {"week_start": "2024-03-11", "actual": 32444.0, "mean_followed": 30036.0, "p90_followed": 30036.0}, {"week_start": "2024-03-18", "actual": 31724.0, "mean_followed": 29970.0, "p90_followed": 29970.0}, {"week_start": "2024-03-25", "actual": 31658.0, "mean_followed": 29966.0, "p90_followed": 29966.0}, {"week_start": "2024-04-01", "actual": 29206.0, "mean_followed": 28874.0, "p90_followed": 28874.0}, {"week_start": "2024-04-08", "actual": 28114.0, "mean_followed": 28778.0, "p90_followed": 28778.0}, {"week_start": "2024-04-15", "actual": 28018.0, "mean_followed": 27290.0, "p90_followed": 27290.0}, {"week_start": "2024-04-22", "actual": 25714.0, "mean_followed": 26439.0, "p90_followed": 26439.0}, {"week_start": "2024-04-29", "actual": 24863.0, "mean_followed": 26307.0, "p90_followed": 26307.0}, {"week_start": "2024-05-06", "actual": 24731.0, "mean_followed": 26043.0, "p90_followed": 26043.0}, {"week_start": "2024-05-13", "actual": 24467.0, "mean_followed": 24237.0, "p90_followed": 24237.0}, {"week_start": "2024-05-20", "actual": 22661.0, "mean_followed": 24147.0, "p90_followed": 24147.0}, {"week_start": "2024-05-27", "actual": 22571.0, "mean_followed": 21944.0, "p90_followed": 21944.0}, {"week_start": "2024-06-03", "actual": 20368.0, "mean_followed": 21932.0, "p90_followed": 21932.0}, {"week_start": "2024-06-10", "actual": 21988.0, "mean_followed": 21932.0, "p90_followed": 21932.0}, {"week_start": "2024-06-17", "actual": 21988.0, "mean_followed": 21883.0, "p90_followed": 21883.0}, {"week_start": "2024-06-24", "actual": 21939.0, "mean_followed": 21589.0, "p90_followed": 21589.0}, {"week_start": "2024-07-01", "actual": 21645.0, "mean_followed": 21529.0, "p90_followed": 21529.0}, {"week_start": "2024-07-08", "actual": 21585.0, "mean_followed": 20491.0, "p90_followed": 20491.0}, {"week_start": "2024-07-15", "actual": 20547.0, "mean_followed": 20485.0, "p90_followed": 20485.0}, {"week_start": "2024-07-22", "actual": 21357.0, "mean_followed": 20370.0, "p90_followed": 20370.0}, {"week_start": "2024-07-29", "actual": 21242.0, "mean_followed": 20328.0, "p90_followed": 20328.0}, {"week_start": "2024-08-05", "actual": 22100.0, "mean_followed": 20256.0, "p90_followed": 20256.0}, {"week_start": "2024-08-12", "actual": 23660.0, "mean_followed": 19528.0, "p90_followed": 19528.0}, {"week_start": "2024-08-19", "actual": 22932.0, "mean_followed": 19480.0, "p90_followed": 19480.0}, {"week_start": "2024-08-26", "actual": 22884.0, "mean_followed": 19480.0, "p90_followed": 19480.0}, {"week_start": "2024-09-02", "actual": 22884.0, "mean_followed": 19480.0, "p90_followed": 19480.0}, {"week_start": "2024-09-09", "actual": 22884.0, "mean_followed": 17188.0, "p90_followed": 17188.0}, {"week_start": "2024-09-16", "actual": 20592.0, "mean_followed": 17146.0, "p90_followed": 17146.0}, {"week_start": "2024-09-23", "actual": 20550.0, "mean_followed": 17074.0, "p90_followed": 17074.0}, {"week_start": "2024-09-30", "actual": 21300.0, "mean_followed": 16324.0, "p90_followed": 16324.0}, {"week_start": "2024-10-07", "actual": 20550.0, "mean_followed": 16273.0, "p90_followed": 16273.0}, {"week_start": "2024-10-14", "actual": 20499.0, "mean_followed": 16267.0, "p90_followed": 16267.0}, {"week_start": "2024-10-21", "actual": 20493.0, "mean_followed": 15511.0, "p90_followed": 15511.0}, {"week_start": "2024-10-28", "actual": 19737.0, "mean_followed": 15463.0, "p90_followed": 15463.0}, {"week_start": "2024-11-04", "actual": 19689.0, "mean_followed": 14671.0, "p90_followed": 14671.0}, {"week_start": "2024-11-11", "actual": 18897.0, "mean_followed": 12169.0, "p90_followed": 12169.0}, {"week_start": "2024-11-18", "actual": 16395.0, "mean_followed": 12127.0, "p90_followed": 12127.0}, {"week_start": "2024-11-25", "actual": 19617.0, "mean_followed": 12079.0, "p90_followed": 12079.0}, {"week_start": "2024-12-02", "actual": 19569.0, "mean_followed": 12079.0, "p90_followed": 12079.0}, {"week_start": "2024-12-09", "actual": 19569.0, "mean_followed": 10495.0, "p90_followed": 10495.0}, {"week_start": "2024-12-16", "actual": 21249.0, "mean_followed": 10436.0, "p90_followed": 10436.0}, {"week_start": "2024-12-23", "actual": 21190.0, "mean_followed": 7718.0, "p90_followed": 7718.0}, {"week_start": "2024-12-30", "actual": 18472.0, "mean_followed": 7370.0, "p90_followed": 7370.0}, {"week_start": "2025-01-06", "actual": 20572.0, "mean_followed": 7286.0, "p90_followed": 7286.0}, {"week_start": "2025-01-13", "actual": 20488.0, "mean_followed": 7052.0, "p90_followed": 7052.0}, {"week_start": "2025-01-20", "actual": 20254.0, "mean_followed": 6290.0, "p90_followed": 6290.0}, {"week_start": "2025-01-27", "actual": 19492.0, "mean_followed": 6290.0, "p90_followed": 6290.0}, {"week_start": "2025-02-03", "actual": 19492.0, "mean_followed": 2672.0, "p90_followed": 9578.0}, {"week_start": "2025-02-10", "actual": 15874.0, "mean_followed": 1046.0, "p90_followed": 7952.0}, {"week_start": "2025-02-17", "actual": 15880.0, "mean_followed": 1022.0, "p90_followed": 7928.0}, {"week_start": "2025-02-24", "actual": 15856.0, "mean_followed": 1022.0, "p90_followed": 7928.0}, {"week_start": "2025-03-03", "actual": 16672.0, "mean_followed": 1010.0, "p90_followed": 7916.0}, {"week_start": "2025-03-10", "actual": 16660.0, "mean_followed": 1007.0, "p90_followed": 7913.0}, {"week_start": "2025-03-17", "actual": 16657.0, "mean_followed": 971.0, "p90_followed": 7877.0}, {"week_start": "2025-03-24", "actual": 16621.0, "mean_followed": 953.0, "p90_followed": 7859.0}, {"week_start": "2025-03-31", "actual": 16843.0, "mean_followed": 904.0, "p90_followed": 12868.0}, {"week_start": "2025-04-07", "actual": 16794.0, "mean_followed": 874.0, "p90_followed": 12838.0}, {"week_start": "2025-04-14", "actual": 16764.0, "mean_followed": -796.0, "p90_followed": 11168.0}, {"week_start": "2025-04-21", "actual": 16894.0, "mean_followed": -946.0, "p90_followed": 11018.0}, {"week_start": "2025-04-28", "actual": 16744.0, "mean_followed": -1012.0, "p90_followed": 10952.0}, {"week_start": "2025-05-05", "actual": 16678.0, "mean_followed": 1694.0, "p90_followed": 14036.0}, {"week_start": "2025-05-12", "actual": 14950.0, "mean_followed": 1322.0, "p90_followed": 13664.0}, {"week_start": "2025-05-19", "actual": 14578.0, "mean_followed": -142.0, "p90_followed": 12200.0}, {"week_start": "2025-05-26", "actual": 13114.0, "mean_followed": -238.0, "p90_followed": 12104.0}, {"week_start": "2025-06-02", "actual": 13018.0, "mean_followed": 1682.0, "p90_followed": 12080.0}, {"week_start": "2025-06-09", "actual": 12994.0, "mean_followed": 1616.0, "p90_followed": 12014.0}, {"week_start": "2025-06-16", "actual": 12928.0, "mean_followed": 1538.0, "p90_followed": 11936.0}, {"week_start": "2025-06-23", "actual": 12850.0, "mean_followed": 1513.0, "p90_followed": 11911.0}, {"week_start": "2025-06-30", "actual": 12825.0, "mean_followed": 1488.0, "p90_followed": 11886.0}, {"week_start": "2025-07-07", "actual": 12800.0, "mean_followed": -180.0, "p90_followed": 10218.0}, {"week_start": "2025-07-14", "actual": 11132.0, "mean_followed": -234.0, "p90_followed": 10164.0}, {"week_start": "2025-07-21", "actual": 12578.0, "mean_followed": -338.0, "p90_followed": 10060.0}, {"week_start": "2025-07-28", "actual": 12474.0, "mean_followed": -2065.0, "p90_followed": 8333.0}, {"week_start": "2025-08-04", "actual": 10747.0, "mean_followed": -2077.0, "p90_followed": 8321.0}, {"week_start": "2025-08-11", "actual": 10735.0, "mean_followed": -2083.0, "p90_followed": 8315.0}, {"week_start": "2025-08-18", "actual": 10729.0, "mean_followed": 2747.0, "p90_followed": 14261.0}, {"week_start": "2025-08-25", "actual": 10639.0, "mean_followed": 2627.0, "p90_followed": 14141.0}, {"week_start": "2025-09-01", "actual": 10519.0, "mean_followed": 2626.0, "p90_followed": 14140.0}, {"week_start": "2025-09-08", "actual": 10518.0, "mean_followed": 2572.0, "p90_followed": 14086.0}, {"week_start": "2025-09-15", "actual": 10464.0, "mean_followed": 2308.0, "p90_followed": 13822.0}, {"week_start": "2025-09-22", "actual": 10200.0, "mean_followed": 340.0, "p90_followed": 11854.0}, {"week_start": "2025-09-29", "actual": 8232.0, "mean_followed": 316.0, "p90_followed": 11830.0}, {"week_start": "2025-10-06", "actual": 8208.0, "mean_followed": -356.0, "p90_followed": 11158.0}, {"week_start": "2025-10-13", "actual": 5904.0, "mean_followed": -416.0, "p90_followed": 11098.0}, {"week_start": "2025-10-20", "actual": 5844.0, "mean_followed": 1216.0, "p90_followed": 15328.0}, {"week_start": "2025-10-27", "actual": 5040.0, "mean_followed": 1096.0, "p90_followed": 15208.0}, {"week_start": "2025-11-03", "actual": 4920.0, "mean_followed": 976.0, "p90_followed": 15088.0}, {"week_start": "2025-11-10", "actual": 4800.0, "mean_followed": -3548.0, "p90_followed": 10564.0}, {"week_start": "2025-11-17", "actual": 276.0, "mean_followed": -1964.0, "p90_followed": 10468.0}, {"week_start": "2025-11-24", "actual": 996.0, "mean_followed": -2288.0, "p90_followed": 10144.0}, {"week_start": "2025-12-01", "actual": 672.0, "mean_followed": -3590.0, "p90_followed": 8842.0}, {"week_start": "2025-12-08", "actual": -630.0, "mean_followed": -3626.0, "p90_followed": 8806.0}, {"week_start": "2025-12-15", "actual": 150.0, "mean_followed": -4412.0, "p90_followed": 8020.0}, {"week_start": "2025-12-22", "actual": -636.0, "mean_followed": -4436.0, "p90_followed": 7996.0}, {"week_start": "2025-12-29", "actual": -660.0, "mean_followed": -4436.0, "p90_followed": 7996.0}, {"week_start": "2026-01-05", "actual": -660.0, "mean_followed": -4436.0, "p90_followed": 7996.0}, {"week_start": "2026-01-12", "actual": 940.0, "mean_followed": -1058.0, "p90_followed": 12940.0}, {"week_start": "2026-01-19", "actual": 940.0, "mean_followed": -1058.0, "p90_followed": 12940.0}, {"week_start": "2026-01-26", "actual": 940.0, "mean_followed": -1058.0, "p90_followed": 12940.0}, {"week_start": "2026-02-02", "actual": 940.0, "mean_followed": -1058.0, "p90_followed": 12940.0}, {"week_start": "2026-02-09", "actual": 940.0, "mean_followed": -1058.0, "p90_followed": 12940.0}, {"week_start": "2026-02-16", "actual": 940.0, "mean_followed": -1058.0, "p90_followed": 12940.0}, {"week_start": "2026-02-23", "actual": 940.0, "mean_followed": -1058.0, "p90_followed": 12940.0}, {"week_start": "2026-03-02", "actual": 940.0, "mean_followed": -1058.0, "p90_followed": 12940.0}, {"week_start": "2026-03-09", "actual": 940.0, "mean_followed": -1058.0, "p90_followed": 12940.0}, {"week_start": "2026-03-16", "actual": 940.0, "mean_followed": -1058.0, "p90_followed": 12940.0}, {"week_start": "2026-03-23", "actual": 940.0, "mean_followed": -1058.0, "p90_followed": 12940.0}, {"week_start": "2026-03-30", "actual": 940.0, "mean_followed": -1058.0, "p90_followed": 12940.0}, {"week_start": "2026-04-06", "actual": 940.0, "mean_followed": -1058.0, "p90_followed": 12940.0}, {"week_start": "2026-04-13", "actual": 940.0, "mean_followed": -1058.0, "p90_followed": 12940.0}, {"week_start": "2026-04-20", "actual": 940.0, "mean_followed": -1058.0, "p90_followed": 12940.0}], "simulated_pos": [{"order_week": "2025-02-03", "arrival_week": "2025-05-05", "qty": 4434.0, "strategy": "mean"}, {"order_week": "2025-03-03", "arrival_week": "2025-06-02", "qty": 1944.0, "strategy": "mean"}, {"order_week": "2025-05-26", "arrival_week": "2025-08-18", "qty": 4920.0, "strategy": "mean"}, {"order_week": "2025-07-21", "arrival_week": "2025-10-20", "qty": 2436.0, "strategy": "mean"}, {"order_week": "2025-08-18", "arrival_week": "2025-11-17", "qty": 1680.0, "strategy": "mean"}, {"order_week": "2025-10-13", "arrival_week": "2026-01-12", "qty": 3378.0, "strategy": "mean"}, {"order_week": "2024-11-11", "arrival_week": "2025-02-03", "qty": 6906.0, "strategy": "p90"}, {"order_week": "2025-01-06", "arrival_week": "2025-03-31", "qty": 5058.0, "strategy": "p90"}, {"order_week": "2025-02-03", "arrival_week": "2025-05-05", "qty": 4812.0, "strategy": "p90"}, {"order_week": "2025-05-26", "arrival_week": "2025-08-18", "qty": 6036.0, "strategy": "p90"}, {"order_week": "2025-07-21", "arrival_week": "2025-10-20", "qty": 5034.0, "strategy": "p90"}, {"order_week": "2025-10-13", "arrival_week": "2026-01-12", "qty": 4944.0, "strategy": "p90"}], "trough_delta": {"actual": -660.0, "mean": -4436.0, "p90": 6290.0}, "narrative": null}