{"sku": "F-04114", "dc": "NJ", "series": [{"week_start": "2023-04-03", "actual": 1179776.0, "mean_followed": 1178504.0, "p90_followed": 1178504.0}, {"week_start": "2023-04-10", "actual": 1178504.0, "mean_followed": 1175132.0, "p90_followed": 1175132.0}, {"week_start": "2023-04-17", "actual": 1175132.0, "mean_followed": 1164338.0, "p90_followed": 1164338.0}, {"week_start": "2023-04-24", "actual": 1164338.0, "mean_followed": 1154246.0, "p90_followed": 1154246.0}, {"week_start": "2023-05-01", "actual": 1154246.0, "mean_followed": 1148249.0, "p90_followed": 1148249.0}, {"week_start": "2023-05-08", "actual": 1148249.0, "mean_followed": 1133524.0, "p90_followed": 1133524.0}, {"week_start": "2023-05-15", "actual": 1133524.0, "mean_followed": 1126451.0, "p90_followed": 1126451.0}, {"week_start": "2023-05-22", "actual": 1126451.0, "mean_followed": 1119391.0, "p90_followed": 1119391.0}, {"week_start": "2023-05-29", "actual": 1119391.0, "mean_followed": 1111369.0, "p90_followed": 1111369.0}, {"week_start": "2023-06-05", "actual": 1111369.0, "mean_followed": 1108105.0, "p90_followed": 1108105.0}, {"week_start": "2023-06-12", "actual": 1108105.0, "mean_followed": 1107154.0, "p90_followed": 1107154.0}, {"week_start": "2023-06-19", "actual": 1112914.0, "mean_followed": 1099180.0, "p90_followed": 1099180.0}, {"week_start": "2023-06-26", "actual": 1104940.0, "mean_followed": 1098951.0, "p90_followed": 1098951.0}, {"week_start": "2023-07-03", "actual": 1112547.0, "mean_followed": 1093856.0, "p90_followed": 1093856.0}, {"week_start": "2023-07-10", "actual": 1107452.0, "mean_followed": 1086392.0, "p90_followed": 1086392.0}, {"week_start": "2023-07-17", "actual": 1099988.0, "mean_followed": 1082522.0, "p90_followed": 1082522.0}, {"week_start": "2023-07-24", "actual": 1096118.0, "mean_followed": 1072655.0, "p90_followed": 1072655.0}, {"week_start": "2023-07-31", "actual": 1086251.0, "mean_followed": 1066469.0, "p90_followed": 1066469.0}, {"week_start": "2023-08-07", "actual": 1080065.0, "mean_followed": 1059749.0, "p90_followed": 1059749.0}, {"week_start": "2023-08-14", "actual": 1073345.0, "mean_followed": 1053773.0, "p90_followed": 1053773.0}, {"week_start": "2023-08-21", "actual": 1067369.0, "mean_followed": 1047382.0, "p90_followed": 1047382.0}, {"week_start": "2023-08-28", "actual": 1060978.0, "mean_followed": 1043590.0, "p90_followed": 1043590.0}, {"week_start": "2023-09-04", "actual": 1057186.0, "mean_followed": 1043228.0, "p90_followed": 1043228.0}, {"week_start": "2023-09-11", "actual": 1056824.0, "mean_followed": 1037591.0, "p90_followed": 1037591.0}, {"week_start": "2023-09-18", "actual": 1051187.0, "mean_followed": 1035071.0, "p90_followed": 1035071.0}, {"week_start": "2023-09-25", "actual": 1071707.0, "mean_followed": 1030824.0, "p90_followed": 1030824.0}, {"week_start": "2023-10-02", "actual": 1067460.0, "mean_followed": 1028280.0, "p90_followed": 1028280.0}, {"week_start": "2023-10-09", "actual": 1064916.0, "mean_followed": 1023672.0, "p90_followed": 1023672.0}, {"week_start": "2023-10-16", "actual": 1064226.0, "mean_followed": 1017428.0, "p90_followed": 1017428.0}, {"week_start": "2023-10-23", "actual": 1057982.0, "mean_followed": 1010619.0, "p90_followed": 1010619.0}, {"week_start": "2023-10-30", "actual": 1051173.0, "mean_followed": 1003989.0, "p90_followed": 1003989.0}, {"week_start": "2023-11-06", "actual": 1044543.0, "mean_followed": 991090.0, "p90_followed": 991090.0}, {"week_start": "2023-11-13", "actual": 1031644.0, "mean_followed": 983230.0, "p90_followed": 983230.0}, {"week_start": "2023-11-20", "actual": 1023784.0, "mean_followed": 975758.0, "p90_followed": 975758.0}, {"week_start": "2023-11-27", "actual": 1016312.0, "mean_followed": 958045.0, "p90_followed": 958045.0}, {"week_start": "2023-12-04", "actual": 998599.0, "mean_followed": 952552.0, "p90_followed": 952552.0}, {"week_start": "2023-12-11", "actual": 993106.0, "mean_followed": 946952.0, "p90_followed": 946952.0}, {"week_start": "2023-12-18", "actual": 1024946.0, "mean_followed": 943328.0, "p90_followed": 943328.0}, {"week_start": "2023-12-25", "actual": 1021322.0, "mean_followed": 932924.0, "p90_followed": 932924.0}, {"week_start": "2024-01-01", "actual": 1010918.0, "mean_followed": 927190.0, "p90_followed": 927190.0}, {"week_start": "2024-01-08", "actual": 1005184.0, "mean_followed": 917608.0, "p90_followed": 917608.0}, {"week_start": "2024-01-15", "actual": 1004242.0, "mean_followed": 914039.0, "p90_followed": 914039.0}, {"week_start": "2024-01-22", "actual": 1000673.0, "mean_followed": 908097.0, "p90_followed": 908097.0}, {"week_start": "2024-01-29", "actual": 994731.0, "mean_followed": 902479.0, "p90_followed": 902479.0}, {"week_start": "2024-02-05", "actual": 1003513.0, "mean_followed": 893485.0, "p90_followed": 893485.0}, {"week_start": "2024-02-12", "actual": 994519.0, "mean_followed": 892092.0, "p90_followed": 892092.0}, {"week_start": "2024-02-19", "actual": 993126.0, "mean_followed": 886671.0, "p90_followed": 886671.0}, {"week_start": "2024-02-26", "actual": 1001301.0, "mean_followed": 862411.0, "p90_followed": 862411.0}, {"week_start": "2024-03-04", "actual": 968401.0, "mean_followed": 843243.0, "p90_followed": 843243.0}, {"week_start": "2024-03-11", "actual": 937713.0, "mean_followed": 833399.0, "p90_followed": 833399.0}, {"week_start": "2024-03-18", "actual": 927869.0, "mean_followed": 818528.0, "p90_followed": 818528.0}, {"week_start": "2024-03-25", "actual": 920834.0, "mean_followed": 810870.0, "p90_followed": 810870.0}, {"week_start": "2024-04-01", "actual": 913176.0, "mean_followed": 801134.0, "p90_followed": 801134.0}, {"week_start": "2024-04-08", "actual": 903440.0, "mean_followed": 791160.0, "p90_followed": 791160.0}, {"week_start": "2024-04-15", "actual": 893466.0, "mean_followed": 782707.0, "p90_followed": 782707.0}, {"week_start": "2024-04-22", "actual": 888931.0, "mean_followed": 773559.0, "p90_followed": 773559.0}, {"week_start": "2024-04-29", "actual": 879783.0, "mean_followed": 757046.0, "p90_followed": 757046.0}, {"week_start": "2024-05-06", "actual": 863270.0, "mean_followed": 748379.0, "p90_followed": 748379.0}, {"week_start": "2024-05-13", "actual": 854603.0, "mean_followed": 744363.0, "p90_followed": 744363.0}, {"week_start": "2024-05-20", "actual": 850587.0, "mean_followed": 727002.0, "p90_followed": 727002.0}, {"week_start": "2024-05-27", "actual": 833226.0, "mean_followed": 720764.0, "p90_followed": 720764.0}, {"week_start": "2024-06-03", "actual": 826988.0, "mean_followed": 706414.0, "p90_followed": 706414.0}, {"week_start": "2024-06-10", "actual": 815218.0, "mean_followed": 694046.0, "p90_followed": 694046.0}, {"week_start": "2024-06-17", "actual": 802850.0, "mean_followed": 681089.0, "p90_followed": 681089.0}, {"week_start": "2024-06-24", "actual": 789893.0, "mean_followed": 669990.0, "p90_followed": 669990.0}, {"week_start": "2024-07-01", "actual": 778794.0, "mean_followed": 659842.0, "p90_followed": 659842.0}, {"week_start": "2024-07-08", "actual": 768646.0, "mean_followed": 651279.0, "p90_followed": 651279.0}, {"week_start": "2024-07-15", "actual": 780243.0, "mean_followed": 641861.0, "p90_followed": 641861.0}, {"week_start": "2024-07-22", "actual": 790985.0, "mean_followed": 631246.0, "p90_followed": 631246.0}, {"week_start": "2024-07-29", "actual": 780370.0, "mean_followed": 620932.0, "p90_followed": 620932.0}, {"week_start": "2024-08-05", "actual": 793096.0, "mean_followed": 613755.0, "p90_followed": 613755.0}, {"week_start": "2024-08-12", "actual": 785919.0, "mean_followed": 601143.0, "p90_followed": 601143.0}, {"week_start": "2024-08-19", "actual": 773307.0, "mean_followed": 589091.0, "p90_followed": 589091.0}, {"week_start": "2024-08-26", "actual": 781415.0, "mean_followed": 573132.0, "p90_followed": 573132.0}, {"week_start": "2024-09-02", "actual": 769374.0, "mean_followed": 572921.0, "p90_followed": 572921.0}, {"week_start": "2024-09-09", "actual": 769163.0, "mean_followed": 568993.0, "p90_followed": 568993.0}, {"week_start": "2024-09-16", "actual": 765235.0, "mean_followed": 560699.0, "p90_followed": 560699.0}, {"week_start": "2024-09-23", "actual": 756941.0, "mean_followed": 549507.0, "p90_followed": 549507.0}, {"week_start": "2024-09-30", "actual": 745749.0, "mean_followed": 540646.0, "p90_followed": 540646.0}, {"week_start": "2024-10-07", "actual": 736888.0, "mean_followed": 533957.0, "p90_followed": 533957.0}, {"week_start": "2024-10-14", "actual": 741719.0, "mean_followed": 528079.0, "p90_followed": 528079.0}, {"week_start": "2024-10-21", "actual": 744481.0, "mean_followed": 520241.0, "p90_followed": 520241.0}, {"week_start": "2024-10-28", "actual": 736643.0, "mean_followed": 517169.0, "p90_followed": 517169.0}, {"week_start": "2024-11-04", "actual": 735533.0, "mean_followed": 513306.0, "p90_followed": 513306.0}, {"week_start": "2024-11-11", "actual": 736572.0, "mean_followed": 500944.0, "p90_followed": 500944.0}, {"week_start": "2024-11-18", "actual": 724210.0, "mean_followed": 482067.0, "p90_followed": 482067.0}, {"week_start": "2024-11-25", "actual": 705333.0, "mean_followed": 473286.0, "p90_followed": 473286.0}, {"week_start": "2024-12-02", "actual": 696552.0, "mean_followed": 459278.0, "p90_followed": 459278.0}, {"week_start": "2024-12-09", "actual": 682544.0, "mean_followed": 450828.0, "p90_followed": 450828.0}, {"week_start": "2024-12-16", "actual": 676056.0, "mean_followed": 432986.0, "p90_followed": 432986.0}, {"week_start": "2024-12-23", "actual": 665450.0, "mean_followed": 423899.0, "p90_followed": 423899.0}, {"week_start": "2024-12-30", "actual": 656363.0, "mean_followed": 401110.0, "p90_followed": 401110.0}, {"week_start": "2025-01-06", "actual": 633574.0, "mean_followed": 397439.0, "p90_followed": 397439.0}, {"week_start": "2025-01-13", "actual": 629903.0, "mean_followed": 384898.0, "p90_followed": 384898.0}, {"week_start": "2025-01-20", "actual": 629116.0, "mean_followed": 368107.0, "p90_followed": 368107.0}, {"week_start": "2025-01-27", "actual": 614075.0, "mean_followed": 361763.0, "p90_followed": 361763.0}, {"week_start": "2025-02-03", "actual": 609687.0, "mean_followed": 348857.0, "p90_followed": 348857.0}, {"week_start": "2025-02-10", "actual": 596781.0, "mean_followed": 328726.0, "p90_followed": 328726.0}, {"week_start": "2025-02-17", "actual": 588404.0, "mean_followed": 313628.0, "p90_followed": 313628.0}, {"week_start": "2025-02-24", "actual": 573306.0, "mean_followed": 301563.0, "p90_followed": 301563.0}, {"week_start": "2025-03-03", "actual": 561241.0, "mean_followed": 280219.0, "p90_followed": 280219.0}, {"week_start": "2025-03-10", "actual": 543815.0, "mean_followed": 272268.0, "p90_followed": 272268.0}, {"week_start": "2025-03-17", "actual": 535864.0, "mean_followed": 258912.0, "p90_followed": 258912.0}, {"week_start": "2025-03-24", "actual": 530344.0, "mean_followed": 243833.0, "p90_followed": 243833.0}, {"week_start": "2025-03-31", "actual": 515265.0, "mean_followed": 237108.0, "p90_followed": 237108.0}, {"week_start": "2025-04-07", "actual": 508540.0, "mean_followed": 229161.0, "p90_followed": 229161.0}, {"week_start": "2025-04-14", "actual": 489073.0, "mean_followed": 216067.0, "p90_followed": 216067.0}, {"week_start": "2025-04-21", "actual": 475979.0, "mean_followed": 192783.0, "p90_followed": 192783.0}, {"week_start": "2025-04-28", "actual": 464449.0, "mean_followed": 182888.0, "p90_followed": 182888.0}, {"week_start": "2025-05-05", "actual": 454554.0, "mean_followed": 166433.0, "p90_followed": 166433.0}, {"week_start": "2025-05-12", "actual": 438099.0, "mean_followed": 160619.0, "p90_followed": 160619.0}, {"week_start": "2025-05-19", "actual": 432285.0, "mean_followed": 148249.0, "p90_followed": 148249.0}, {"week_start": "2025-05-26", "actual": 419915.0, "mean_followed": 134045.0, "p90_followed": 134045.0}, {"week_start": "2025-06-02", "actual": 405711.0, "mean_followed": 131656.0, "p90_followed": 131656.0}, {"week_start": "2025-06-09", "actual": 403322.0, "mean_followed": 121162.0, "p90_followed": 121162.0}, {"week_start": "2025-06-16", "actual": 392828.0, "mean_followed": 114813.0, "p90_followed": 114813.0}, {"week_start": "2025-06-23", "actual": 386479.0, "mean_followed": 103725.0, "p90_followed": 103725.0}, {"week_start": "2025-06-30", "actual": 375391.0, "mean_followed": 99408.0, "p90_followed": 176100.0}, {"week_start": "2025-07-07", "actual": 371074.0, "mean_followed": 85657.0, "p90_followed": 162349.0}, {"week_start": "2025-07-14", "actual": 357323.0, "mean_followed": 81871.0, "p90_followed": 158563.0}, {"week_start": "2025-07-21", "actual": 353537.0, "mean_followed": 75796.0, "p90_followed": 152488.0}, {"week_start": "2025-07-28", "actual": 347462.0, "mean_followed": 71570.0, "p90_followed": 148262.0}, {"week_start": "2025-08-04", "actual": 343236.0, "mean_followed": 56824.0, "p90_followed": 133516.0}, {"week_start": "2025-08-11", "actual": 328490.0, "mean_followed": 39291.0, "p90_followed": 115983.0}, {"week_start": "2025-08-18", "actual": 310957.0, "mean_followed": 23082.0, "p90_followed": 99774.0}, {"week_start": "2025-08-25", "actual": 294748.0, "mean_followed": 8404.0, "p90_followed": 85096.0}, {"week_start": "2025-09-01", "actual": 280070.0, "mean_followed": 1985.0, "p90_followed": 186629.0}, {"week_start": "2025-09-08", "actual": 273651.0, "mean_followed": -7613.0, "p90_followed": 177031.0}, {"week_start": "2025-09-15", "actual": 264053.0, "mean_followed": -18212.0, "p90_followed": 166432.0}, {"week_start": "2025-09-22", "actual": 253454.0, "mean_followed": -24141.0, "p90_followed": 160503.0}, {"week_start": "2025-09-29", "actual": 247525.0, "mean_followed": -36763.0, "p90_followed": 147881.0}, {"week_start": "2025-10-06", "actual": 237403.0, "mean_followed": -41400.0, "p90_followed": 143244.0}, {"week_start": "2025-10-13", "actual": 232766.0, "mean_followed": -52418.0, "p90_followed": 132226.0}, {"week_start": "2025-10-20", "actual": 229498.0, "mean_followed": 16402.0, "p90_followed": 219262.0}, {"week_start": "2025-10-27", "actual": 222730.0, "mean_followed": 11925.0, "p90_followed": 214785.0}, {"week_start": "2025-11-03", "actual": 218253.0, "mean_followed": 1873.0, "p90_followed": 204733.0}, {"week_start": "2025-11-10", "actual": 208201.0, "mean_followed": -12504.0, "p90_followed": 190356.0}, {"week_start": "2025-11-17", "actual": 193824.0, "mean_followed": 23854.0, "p90_followed": 177538.0}, {"week_start": "2025-11-24", "actual": 181006.0, "mean_followed": 16376.0, "p90_followed": 170060.0}, {"week_start": "2025-12-01", "actual": 176278.0, "mean_followed": 12534.0, "p90_followed": 166218.0}, {"week_start": "2025-12-08", "actual": 172436.0, "mean_followed": 4914.0, "p90_followed": 158598.0}, {"week_start": "2025-12-15", "actual": 164816.0, "mean_followed": -3630.0, "p90_followed": 215598.0}, {"week_start": "2025-12-22", "actual": 156272.0, "mean_followed": -14295.0, "p90_followed": 204933.0}, {"week_start": "2025-12-29", "actual": 145607.0, "mean_followed": -21700.0, "p90_followed": 197528.0}, {"week_start": "2026-01-05", "actual": 138202.0, "mean_followed": -21700.0, "p90_followed": 197528.0}, {"week_start": "2026-01-12", "actual": 138202.0, "mean_followed": 34004.0, "p90_followed": 197528.0}, {"week_start": "2026-01-19", "actual": 138202.0, "mean_followed": 34004.0, "p90_followed": 197528.0}, {"week_start": "2026-01-26", "actual": 138202.0, "mean_followed": 34004.0, "p90_followed": 197528.0}, {"week_start": "2026-02-02", "actual": 138202.0, "mean_followed": 34004.0, "p90_followed": 197528.0}, {"week_start": "2026-02-09", "actual": 138202.0, "mean_followed": 87080.0, "p90_followed": 287384.0}, {"week_start": "2026-02-16", "actual": 138202.0, "mean_followed": 87080.0, "p90_followed": 287384.0}, {"week_start": "2026-02-23", "actual": 138202.0, "mean_followed": 87080.0, "p90_followed": 287384.0}, {"week_start": "2026-03-02", "actual": 138202.0, "mean_followed": 87080.0, "p90_followed": 287384.0}, {"week_start": "2026-03-09", "actual": 138202.0, "mean_followed": 130412.0, "p90_followed": 287384.0}, {"week_start": "2026-03-16", "actual": 138202.0, "mean_followed": 130412.0, "p90_followed": 287384.0}, {"week_start": "2026-03-23", "actual": 138202.0, "mean_followed": 130412.0, "p90_followed": 287384.0}, {"week_start": "2026-03-30", "actual": 138202.0, "mean_followed": 130412.0, "p90_followed": 287384.0}, {"week_start": "2026-04-06", "actual": 138202.0, "mean_followed": 130412.0, "p90_followed": 367220.0}, {"week_start": "2026-04-13", "actual": 138202.0, "mean_followed": 130412.0, "p90_followed": 367220.0}, {"week_start": "2026-04-20", "actual": 138202.0, "mean_followed": 130412.0, "p90_followed": 367220.0}], "simulated_pos": [{"order_week": "2025-04-28", "arrival_week": "2025-10-20", "qty": 75588.0, "strategy": "mean"}, {"order_week": "2025-05-26", "arrival_week": "2025-11-17", "qty": 49176.0, "strategy": "mean"}, {"order_week": "2025-07-21", "arrival_week": "2026-01-12", "qty": 55704.0, "strategy": "mean"}, {"order_week": "2025-08-18", "arrival_week": "2026-02-09", "qty": 53076.0, "strategy": "mean"}, {"order_week": "2025-09-15", "arrival_week": "2026-03-09", "qty": 43332.0, "strategy": "mean"}, {"order_week": "2025-01-06", "arrival_week": "2025-06-30", "qty": 76692.0, "strategy": "p90"}, {"order_week": "2025-03-03", "arrival_week": "2025-09-01", "qty": 107952.0, "strategy": "p90"}, {"order_week": "2025-04-28", "arrival_week": "2025-10-20", "qty": 93804.0, "strategy": "p90"}, {"order_week": "2025-06-23", "arrival_week": "2025-12-15", "qty": 65544.0, "strategy": "p90"}, {"order_week": "2025-08-18", "arrival_week": "2026-02-09", "qty": 89856.0, "strategy": "p90"}, {"order_week": "2025-10-13", "arrival_week": "2026-04-06", "qty": 79836.0, "strategy": "p90"}], "trough_delta": {"actual": 138202.0, "mean": -52418.0, "p90": 85096.0}, "narrative": null}