{"sku": "F-04221", "dc": "NJ", "series": [{"week_start": "2024-10-14", "actual": 48673.0, "mean_followed": 48495.0, "p90_followed": 48495.0}, {"week_start": "2024-10-21", "actual": 48495.0, "mean_followed": 48495.0, "p90_followed": 48495.0}, {"week_start": "2024-10-28", "actual": 48495.0, "mean_followed": 44522.0, "p90_followed": 44522.0}, {"week_start": "2024-11-04", "actual": 44522.0, "mean_followed": 44149.0, "p90_followed": 44149.0}, {"week_start": "2024-11-11", "actual": 44149.0, "mean_followed": 43860.0, "p90_followed": 43860.0}, {"week_start": "2024-11-18", "actual": 43860.0, "mean_followed": 42929.0, "p90_followed": 42929.0}, {"week_start": "2024-11-25", "actual": 42929.0, "mean_followed": 41223.0, "p90_followed": 41223.0}, {"week_start": "2024-12-02", "actual": 41223.0, "mean_followed": 38866.0, "p90_followed": 38866.0}, {"week_start": "2024-12-09", "actual": 38866.0, "mean_followed": 38866.0, "p90_followed": 38866.0}, {"week_start": "2024-12-16", "actual": 38866.0, "mean_followed": 38866.0, "p90_followed": 38866.0}, {"week_start": "2024-12-23", "actual": 38866.0, "mean_followed": 38866.0, "p90_followed": 38866.0}, {"week_start": "2024-12-30", "actual": 38866.0, "mean_followed": 38866.0, "p90_followed": 38866.0}, {"week_start": "2025-01-06", "actual": 38866.0, "mean_followed": 38866.0, "p90_followed": 38866.0}, {"week_start": "2025-01-13", "actual": 38866.0, "mean_followed": 38866.0, "p90_followed": 38866.0}, {"week_start": "2025-01-20", "actual": 38866.0, "mean_followed": 38866.0, "p90_followed": 38866.0}, {"week_start": "2025-01-27", "actual": 38866.0, "mean_followed": 38866.0, "p90_followed": 38866.0}, {"week_start": "2025-02-03", "actual": 38866.0, "mean_followed": 38866.0, "p90_followed": 38866.0}, {"week_start": "2025-02-10", "actual": 38866.0, "mean_followed": 34431.0, "p90_followed": 59413.54987707973}, {"week_start": "2025-02-17", "actual": 34431.0, "mean_followed": 33994.0, "p90_followed": 58976.54987707973}, {"week_start": "2025-02-24", "actual": 33994.0, "mean_followed": 33994.0, "p90_followed": 58976.54987707973}, {"week_start": "2025-03-03", "actual": 33994.0, "mean_followed": 33994.0, "p90_followed": 58976.54987707973}, {"week_start": "2025-03-10", "actual": 33994.0, "mean_followed": 29097.0, "p90_followed": 54079.54987707973}, {"week_start": "2025-03-17", "actual": 29097.0, "mean_followed": 29097.0, "p90_followed": 54079.54987707973}, {"week_start": "2025-03-24", "actual": 29097.0, "mean_followed": 29097.0, "p90_followed": 54079.54987707973}, {"week_start": "2025-03-31", "actual": 29097.0, "mean_followed": 29097.0, "p90_followed": 54079.54987707973}, {"week_start": "2025-04-07", "actual": 29097.0, "mean_followed": 29097.0, "p90_followed": 54079.54987707973}, {"week_start": "2025-04-14", "actual": 29097.0, "mean_followed": 29097.0, "p90_followed": 54079.54987707973}, {"week_start": "2025-04-21", "actual": 29097.0, "mean_followed": 29097.0, "p90_followed": 54079.54987707973}, {"week_start": "2025-04-28", "actual": 29097.0, "mean_followed": 29097.0, "p90_followed": 54079.54987707973}, {"week_start": "2025-05-05", "actual": 29097.0, "mean_followed": 27324.0, "p90_followed": 52306.54987707973}, {"week_start": "2025-05-12", "actual": 27324.0, "mean_followed": 25668.0, "p90_followed": 50650.54987707973}, {"week_start": "2025-05-19", "actual": 25668.0, "mean_followed": 25668.0, "p90_followed": 50650.54987707973}, {"week_start": "2025-05-26", "actual": 25668.0, "mean_followed": 25668.0, "p90_followed": 50650.54987707973}, {"week_start": "2025-06-02", "actual": 25668.0, "mean_followed": 25668.0, "p90_followed": 66629.10013901127}, {"week_start": "2025-06-09", "actual": 25668.0, "mean_followed": 25668.0, "p90_followed": 66629.10013901127}, {"week_start": "2025-06-16", "actual": 25668.0, "mean_followed": 25668.0, "p90_followed": 66629.10013901127}, {"week_start": "2025-06-23", "actual": 25668.0, "mean_followed": 25668.0, "p90_followed": 66629.10013901127}, {"week_start": "2025-06-30", "actual": 25668.0, "mean_followed": 37506.189038615, "p90_followed": 66629.10013901127}, {"week_start": "2025-07-07", "actual": 25668.0, "mean_followed": 37506.189038615, "p90_followed": 66629.10013901127}, {"week_start": "2025-07-14", "actual": 25668.0, "mean_followed": 37506.189038615, "p90_followed": 66629.10013901127}, {"week_start": "2025-07-21", "actual": 25668.0, "mean_followed": 37032.189038615, "p90_followed": 66155.10013901127}, {"week_start": "2025-07-28", "actual": 25194.0, "mean_followed": 33100.189038615, "p90_followed": 62223.100139011265}, {"week_start": "2025-08-04", "actual": 21262.0, "mean_followed": 31236.189038614997, "p90_followed": 60359.100139011265}, {"week_start": "2025-08-11", "actual": 19398.0, "mean_followed": 31236.189038614997, "p90_followed": 60359.100139011265}, {"week_start": "2025-08-18", "actual": 19398.0, "mean_followed": 30303.189038614997, "p90_followed": 59426.100139011265}, {"week_start": "2025-08-25", "actual": 18465.0, "mean_followed": 25082.189038614997, "p90_followed": 54205.100139011265}, {"week_start": "2025-09-01", "actual": 13244.0, "mean_followed": 25082.189038614997, "p90_followed": 54205.100139011265}, {"week_start": "2025-09-08", "actual": 13244.0, "mean_followed": 25082.189038614997, "p90_followed": 54205.100139011265}, {"week_start": "2025-09-15", "actual": 13244.0, "mean_followed": 25082.189038614997, "p90_followed": 54205.100139011265}, {"week_start": "2025-09-22", "actual": 13244.0, "mean_followed": 24838.189038614997, "p90_followed": 53961.100139011265}, {"week_start": "2025-09-29", "actual": 13000.0, "mean_followed": 22863.189038614997, "p90_followed": 51986.100139011265}, {"week_start": "2025-10-06", "actual": 11025.0, "mean_followed": 21696.189038614997, "p90_followed": 50819.100139011265}, {"week_start": "2025-10-13", "actual": 9858.0, "mean_followed": 21696.189038614997, "p90_followed": 50819.100139011265}, {"week_start": "2025-10-20", "actual": 9858.0, "mean_followed": 21696.189038614997, "p90_followed": 50819.100139011265}, {"week_start": "2025-10-27", "actual": 9858.0, "mean_followed": 21696.189038614997, "p90_followed": 50819.100139011265}, {"week_start": "2025-11-03", "actual": 9858.0, "mean_followed": 21696.189038614997, "p90_followed": 50819.100139011265}, {"week_start": "2025-11-10", "actual": 9858.0, "mean_followed": 21696.189038614997, "p90_followed": 50819.100139011265}, {"week_start": "2025-11-17", "actual": 9858.0, "mean_followed": 31733.497677265434, "p90_followed": 70357.24223282101}, {"week_start": "2025-11-24", "actual": 9534.0, "mean_followed": 29354.497677265434, "p90_followed": 67978.24223282101}, {"week_start": "2025-12-01", "actual": 7155.0, "mean_followed": 28950.497677265434, "p90_followed": 67574.24223282101}, {"week_start": "2025-12-08", "actual": 6751.0, "mean_followed": 28950.497677265434, "p90_followed": 67574.24223282101}, {"week_start": "2025-12-15", "actual": 6751.0, "mean_followed": 36408.19537277612, "p90_followed": 67046.24223282101}, {"week_start": "2025-12-22", "actual": 6223.0, "mean_followed": 36165.19537277612, "p90_followed": 66803.24223282101}, {"week_start": "2025-12-29", "actual": 5980.0, "mean_followed": 33285.19537277612, "p90_followed": 63923.24223282101}, {"week_start": "2026-01-05", "actual": 3100.0, "mean_followed": 33285.19537277612, "p90_followed": 63923.24223282101}, {"week_start": "2026-01-12", "actual": 3100.0, "mean_followed": 33285.19537277612, "p90_followed": 63923.24223282101}, {"week_start": "2026-01-19", "actual": 3100.0, "mean_followed": 33285.19537277612, "p90_followed": 63923.24223282101}, {"week_start": "2026-01-26", "actual": 3100.0, "mean_followed": 33285.19537277612, "p90_followed": 63923.24223282101}, {"week_start": "2026-02-02", "actual": 3100.0, "mean_followed": 33285.19537277612, "p90_followed": 63923.24223282101}, {"week_start": "2026-02-09", "actual": 3100.0, "mean_followed": 33285.19537277612, "p90_followed": 63923.24223282101}, {"week_start": "2026-02-16", "actual": 3100.0, "mean_followed": 33285.19537277612, "p90_followed": 63923.24223282101}, {"week_start": "2026-02-23", "actual": 3100.0, "mean_followed": 33285.19537277612, "p90_followed": 63923.24223282101}, {"week_start": "2026-03-02", "actual": 3100.0, "mean_followed": 33285.19537277612, "p90_followed": 63923.24223282101}, {"week_start": "2026-03-09", "actual": 3100.0, "mean_followed": 33285.19537277612, "p90_followed": 63923.24223282101}, {"week_start": "2026-03-16", "actual": 3100.0, "mean_followed": 33285.19537277612, "p90_followed": 63923.24223282101}, {"week_start": "2026-03-23", "actual": 3100.0, "mean_followed": 33285.19537277612, "p90_followed": 63923.24223282101}, {"week_start": "2026-03-30", "actual": 3100.0, "mean_followed": 33285.19537277612, "p90_followed": 63923.24223282101}, {"week_start": "2026-04-06", "actual": 3100.0, "mean_followed": 33285.19537277612, "p90_followed": 63923.24223282101}, {"week_start": "2026-04-13", "actual": 3100.0, "mean_followed": 33285.19537277612, "p90_followed": 63923.24223282101}, {"week_start": "2026-04-20", "actual": 3100.0, "mean_followed": 33285.19537277612, "p90_followed": 63923.24223282101}], "simulated_pos": [{"order_week": "2025-03-31", "arrival_week": "2025-06-30", "qty": 11838.189038614997, "strategy": "mean"}, {"order_week": "2025-08-18", "arrival_week": "2025-11-17", "qty": 10361.308638650436, "strategy": "mean"}, {"order_week": "2025-09-15", "arrival_week": "2025-12-15", "qty": 7985.6976955106875, "strategy": "mean"}, {"order_week": "2024-11-11", "arrival_week": "2025-02-10", "qty": 24982.549877079728, "strategy": "p90"}, {"order_week": "2025-03-03", "arrival_week": "2025-06-02", "qty": 15978.550261931538, "strategy": "p90"}, {"order_week": "2025-08-18", "arrival_week": "2025-11-17", "qty": 19862.142093809744, "strategy": "p90"}], "trough_delta": {"actual": 3100.0, "mean": 21696.189038614997, "p90": 38866.0}, "narrative": null}