{"sku": "F-04114", "dc": "LA", "weekly": [{"week_start": "2023-01-02", "MM": 48.0, "AM": 0.0, "HF": 156.0}, {"week_start": "2023-01-09", "MM": 612.0, "AM": 0.0, "HF": 0.0}, {"week_start": "2023-01-16", "MM": 52.0, "AM": 0.0, "HF": 0.0}, {"week_start": "2023-01-23", "MM": 64.0, "AM": 0.0, "HF": 252.0}, {"week_start": "2023-01-30", "MM": 36.0, "AM": 0.0, "HF": 72.0}, {"week_start": "2023-02-06", "MM": 13.0, "AM": 0.0, "HF": 0.0}, {"week_start": "2023-02-13", "MM": 144.0, "AM": 0.0, "HF": 0.0}, {"week_start": "2023-02-20", "MM": 48.0, "AM": 0.0, "HF": 0.0}, {"week_start": "2023-02-27", "MM": 192.0, "AM": 0.0, "HF": 0.0}, {"week_start": "2023-03-06", "MM": 360.0, "AM": 0.0, "HF": 0.0}, {"week_start": "2023-03-13", "MM": 1.0, "AM": 0.0, "HF": 0.0}, {"week_start": "2023-03-27", "MM": 96.0, "AM": 0.0, "HF": 0.0}, {"week_start": "2023-04-10", "MM": 144.0, "AM": 0.0, "HF": 144.0}, {"week_start": "2023-04-17", "MM": 132.0, "AM": 0.0, "HF": 84.0}, {"week_start": "2023-04-24", "MM": 43.0, "AM": 0.0, "HF": 180.0}, {"week_start": "2023-05-01", "MM": 36.0, "AM": 0.0, "HF": 2136.0}, {"week_start": "2023-05-08", "MM": 12.0, "AM": 0.0, "HF": 0.0}, {"week_start": "2023-05-15", "MM": 396.0, "AM": 0.0, "HF": 2136.0}, {"week_start": "2023-05-22", "MM": 96.0, "AM": 0.0, "HF": 0.0}, {"week_start": "2023-05-29", "MM": 0.0, "AM": 0.0, "HF": 204.0}, {"week_start": "2023-06-05", "MM": 377.0, "AM": 0.0, "HF": 0.0}, {"week_start": "2023-06-12", "MM": 180.0, "AM": 0.0, "HF": 0.0}, {"week_start": "2023-06-19", "MM": 132.0, "AM": 0.0, "HF": 0.0}, {"week_start": "2023-06-26", "MM": 41.0, "AM": 0.0, "HF": 0.0}, {"week_start": "2023-07-10", "MM": 169.0, "AM": 0.0, "HF": 0.0}, {"week_start": "2023-07-17", "MM": 84.0, "AM": 0.0, "HF": 0.0}, {"week_start": "2023-07-31", "MM": 96.0, "AM": 0.0, "HF": 0.0}, {"week_start": "2023-08-07", "MM": 252.0, "AM": 0.0, "HF": 612.0}, {"week_start": "2023-08-14", "MM": 17.0, "AM": 0.0, "HF": 0.0}, {"week_start": "2023-08-21", "MM": 36.0, "AM": 0.0, "HF": 12.0}, {"week_start": "2023-08-28", "MM": 0.0, "AM": 0.0, "HF": 288.0}, {"week_start": "2023-09-04", "MM": 48.0, "AM": 240.0, "HF": 0.0}, {"week_start": "2023-09-11", "MM": 24.0, "AM": 36.0, "HF": 0.0}, {"week_start": "2023-09-18", "MM": 60.0, "AM": 84.0, "HF": 0.0}, {"week_start": "2023-09-25", "MM": 120.0, "AM": 228.0, "HF": 0.0}, {"week_start": "2023-10-02", "MM": 168.0, "AM": 168.0, "HF": 0.0}, {"week_start": "2023-10-09", "MM": 84.0, "AM": 96.0, "HF": 0.0}, {"week_start": "2023-10-16", "MM": 108.0, "AM": 228.0, "HF": 0.0}, {"week_start": "2023-10-23", "MM": 36.0, "AM": 96.0, "HF": 0.0}, {"week_start": "2023-10-30", "MM": 12.0, "AM": 132.0, "HF": 12.0}, {"week_start": "2023-11-06", "MM": 156.0, "AM": 144.0, "HF": 300.0}, {"week_start": "2023-11-13", "MM": 252.0, "AM": 300.0, "HF": 0.0}, {"week_start": "2023-11-20", "MM": 276.0, "AM": 444.0, "HF": 0.0}, {"week_start": "2023-11-27", "MM": 540.0, "AM": 408.0, "HF": 600.0}, {"week_start": "2023-12-04", "MM": 96.0, "AM": 372.0, "HF": 2136.0}, {"week_start": "2023-12-11", "MM": 12.0, "AM": 48.0, "HF": 0.0}, {"week_start": "2023-12-18", "MM": 120.0, "AM": 48.0, "HF": 2136.0}, {"week_start": "2023-12-25", "MM": 108.0, "AM": 864.0, "HF": 2136.0}, {"week_start": "2024-01-01", "MM": 181.0, "AM": 420.0, "HF": 0.0}, {"week_start": "2024-01-08", "MM": 144.0, "AM": 852.0, "HF": 0.0}, {"week_start": "2024-01-15", "MM": 12.0, "AM": 72.0, "HF": 0.0}, {"week_start": "2024-01-22", "MM": 158.0, "AM": 732.0, "HF": 912.0}, {"week_start": "2024-01-29", "MM": 347.0, "AM": 348.0, "HF": 0.0}, {"week_start": "2024-02-05", "MM": 60.0, "AM": 684.0, "HF": 0.0}, {"week_start": "2024-02-12", "MM": 326.0, "AM": 132.0, "HF": 0.0}, {"week_start": "2024-02-19", "MM": 0.0, "AM": 48.0, "HF": 0.0}, {"week_start": "2024-02-26", "MM": 0.0, "AM": 12.0, "HF": 0.0}, {"week_start": "2024-03-04", "MM": 33.0, "AM": 744.0, "HF": 2136.0}, {"week_start": "2024-03-11", "MM": 397.0, "AM": 312.0, "HF": 4140.0}, {"week_start": "2024-03-25", "MM": 1620.0, "AM": 588.0, "HF": 0.0}, {"week_start": "2024-04-01", "MM": 1368.0, "AM": 312.0, "HF": 0.0}, {"week_start": "2024-04-08", "MM": 252.0, "AM": 540.0, "HF": 300.0}, {"week_start": "2024-04-15", "MM": 432.0, "AM": 468.0, "HF": 0.0}, {"week_start": "2024-04-22", "MM": 192.0, "AM": 528.0, "HF": 300.0}, {"week_start": "2024-04-29", "MM": 692.0, "AM": 408.0, "HF": 0.0}, {"week_start": "2024-05-06", "MM": 431.0, "AM": 672.0, "HF": 0.0}, {"week_start": "2024-05-13", "MM": 852.0, "AM": 360.0, "HF": 0.0}, {"week_start": "2024-05-20", "MM": 1092.0, "AM": 1428.0, "HF": 0.0}, {"week_start": "2024-05-27", "MM": 564.0, "AM": 396.0, "HF": 0.0}, {"week_start": "2024-06-03", "MM": 1134.0, "AM": 2160.0, "HF": 0.0}, {"week_start": "2024-06-10", "MM": 756.0, "AM": 432.0, "HF": 0.0}, {"week_start": "2024-06-17", "MM": 3019.0, "AM": 624.0, "HF": 300.0}, {"week_start": "2024-06-24", "MM": 648.0, "AM": 816.0, "HF": 0.0}, {"week_start": "2024-07-01", "MM": 301.0, "AM": 528.0, "HF": 0.0}, {"week_start": "2024-07-08", "MM": 2172.0, "AM": 216.0, "HF": 0.0}, {"week_start": "2024-07-15", "MM": 349.0, "AM": 324.0, "HF": 0.0}, {"week_start": "2024-07-22", "MM": 1440.0, "AM": 516.0, "HF": 0.0}, {"week_start": "2024-07-29", "MM": 1128.0, "AM": 72.0, "HF": 0.0}, {"week_start": "2024-08-05", "MM": 786.0, "AM": 144.0, "HF": 0.0}, {"week_start": "2024-08-12", "MM": 919.0, "AM": 972.0, "HF": 0.0}, {"week_start": "2024-08-19", "MM": 1464.0, "AM": 312.0, "HF": 0.0}, {"week_start": "2024-09-09", "MM": 1068.0, "AM": 516.0, "HF": 0.0}, {"week_start": "2024-09-16", "MM": 1164.0, "AM": 492.0, "HF": 0.0}, {"week_start": "2024-09-23", "MM": 1235.0, "AM": 420.0, "HF": 0.0}, {"week_start": "2024-09-30", "MM": 876.0, "AM": 744.0, "HF": 0.0}, {"week_start": "2024-10-07", "MM": 74.0, "AM": 516.0, "HF": 0.0}, {"week_start": "2024-10-14", "MM": 627.0, "AM": 528.0, "HF": 0.0}, {"week_start": "2024-10-21", "MM": 953.0, "AM": 228.0, "HF": 0.0}, {"week_start": "2024-10-28", "MM": 987.0, "AM": 216.0, "HF": 0.0}, {"week_start": "2024-11-04", "MM": 264.0, "AM": 96.0, "HF": 0.0}, {"week_start": "2024-11-11", "MM": 576.0, "AM": 1224.0, "HF": 2136.0}, {"week_start": "2024-11-18", "MM": 3684.0, "AM": 552.0, "HF": 2136.0}, {"week_start": "2024-11-25", "MM": 1788.0, "AM": 204.0, "HF": 0.0}, {"week_start": "2024-12-02", "MM": 276.0, "AM": 180.0, "HF": 0.0}, {"week_start": "2024-12-09", "MM": 624.0, "AM": 192.0, "HF": 0.0}, {"week_start": "2024-12-16", "MM": 926.0, "AM": 384.0, "HF": 0.0}, {"week_start": "2024-12-23", "MM": 1104.0, "AM": 348.0, "HF": 0.0}, {"week_start": "2024-12-30", "MM": 288.0, "AM": 408.0, "HF": 0.0}, {"week_start": "2025-01-06", "MM": 1044.0, "AM": 684.0, "HF": 0.0}, {"week_start": "2025-01-13", "MM": 1128.0, "AM": 432.0, "HF": 0.0}, {"week_start": "2025-01-20", "MM": 934.0, "AM": 600.0, "HF": 0.0}, {"week_start": "2025-01-27", "MM": 1032.0, "AM": 218.0, "HF": 0.0}, {"week_start": "2025-02-03", "MM": 1476.0, "AM": 264.0, "HF": 612.0}, {"week_start": "2025-02-10", "MM": 1284.0, "AM": 444.0, "HF": 0.0}, {"week_start": "2025-02-17", "MM": 4.0, "AM": 672.0, "HF": 0.0}, {"week_start": "2025-02-24", "MM": 360.0, "AM": 624.0, "HF": 0.0}, {"week_start": "2025-03-03", "MM": 1540.0, "AM": 648.0, "HF": 0.0}, {"week_start": "2025-03-10", "MM": 2748.0, "AM": 360.0, "HF": 0.0}, {"week_start": "2025-03-17", "MM": 1190.0, "AM": 396.0, "HF": 0.0}, {"week_start": "2025-03-24", "MM": 1536.0, "AM": 504.0, "HF": 0.0}, {"week_start": "2025-03-31", "MM": 1429.0, "AM": 288.0, "HF": 0.0}, {"week_start": "2025-04-07", "MM": 1404.0, "AM": 528.0, "HF": 0.0}, {"week_start": "2025-04-14", "MM": 1516.0, "AM": 576.0, "HF": 0.0}, {"week_start": "2025-04-21", "MM": 48.0, "AM": 708.0, "HF": 0.0}, {"week_start": "2025-04-28", "MM": 1668.0, "AM": 480.0, "HF": 0.0}, {"week_start": "2025-05-05", "MM": 1680.0, "AM": 408.0, "HF": 0.0}, {"week_start": "2025-05-12", "MM": 1224.0, "AM": 384.0, "HF": 0.0}, {"week_start": "2025-05-19", "MM": 1812.0, "AM": 396.0, "HF": 0.0}, {"week_start": "2025-05-26", "MM": 1500.0, "AM": 672.0, "HF": 0.0}, {"week_start": "2025-06-02", "MM": 703.0, "AM": 720.0, "HF": 0.0}, {"week_start": "2025-06-09", "MM": 1356.0, "AM": 144.0, "HF": 0.0}, {"week_start": "2025-06-16", "MM": 1128.0, "AM": 360.0, "HF": 0.0}, {"week_start": "2025-06-23", "MM": 1296.0, "AM": 312.0, "HF": 0.0}, {"week_start": "2025-06-30", "MM": 72.0, "AM": 313.0, "HF": 0.0}, {"week_start": "2025-07-07", "MM": 2496.0, "AM": 408.0, "HF": 0.0}, {"week_start": "2025-07-14", "MM": 1404.0, "AM": 420.0, "HF": 0.0}, {"week_start": "2025-07-21", "MM": 1968.0, "AM": 348.0, "HF": 0.0}, {"week_start": "2025-07-28", "MM": 1140.0, "AM": 528.0, "HF": 0.0}, {"week_start": "2025-08-04", "MM": 1164.0, "AM": 228.0, "HF": 0.0}, {"week_start": "2025-08-11", "MM": 1344.0, "AM": 192.0, "HF": 0.0}, {"week_start": "2025-08-18", "MM": 1501.0, "AM": 768.0, "HF": 0.0}, {"week_start": "2025-08-25", "MM": 1200.0, "AM": 180.0, "HF": 0.0}, {"week_start": "2025-09-01", "MM": 144.0, "AM": 60.0, "HF": 0.0}, {"week_start": "2025-09-08", "MM": 1392.0, "AM": 840.0, "HF": 2136.0}, {"week_start": "2025-09-15", "MM": 1764.0, "AM": 48.0, "HF": 0.0}, {"week_start": "2025-09-22", "MM": 2868.0, "AM": 408.0, "HF": 0.0}, {"week_start": "2025-09-29", "MM": 1476.0, "AM": 300.0, "HF": 0.0}, {"week_start": "2025-10-06", "MM": 1536.0, "AM": 504.0, "HF": 0.0}, {"week_start": "2025-10-13", "MM": 1848.0, "AM": 372.0, "HF": 0.0}, {"week_start": "2025-10-20", "MM": 1092.0, "AM": 312.0, "HF": 0.0}, {"week_start": "2025-10-27", "MM": 1752.0, "AM": 636.0, "HF": 0.0}, {"week_start": "2025-11-03", "MM": 1056.0, "AM": 180.0, "HF": 2388.0}, {"week_start": "2025-11-10", "MM": 1525.0, "AM": 336.0, "HF": 2136.0}, {"week_start": "2025-11-17", "MM": 1656.0, "AM": 396.0, "HF": 0.0}, {"week_start": "2025-11-24", "MM": 1560.0, "AM": 144.0, "HF": 0.0}, {"week_start": "2025-12-01", "MM": 1608.0, "AM": 180.0, "HF": 0.0}, {"week_start": "2025-12-08", "MM": 2064.0, "AM": 300.0, "HF": 0.0}, {"week_start": "2025-12-15", "MM": 1776.0, "AM": 816.0, "HF": 4284.0}, {"week_start": "2025-12-22", "MM": 156.0, "AM": 528.0, "HF": 0.0}, {"week_start": "2025-12-29", "MM": 324.0, "AM": 60.0, "HF": 4284.0}], "top_customers": [{"custnmbr": "MSA608A", "name": "MSA608A", "share_pct": 65.0661689854089, "qty": 92040.0}, {"custnmbr": "WAO556A", "name": "WAO556A", "share_pct": 25.593824228028506, "qty": 36204.0}, {"custnmbr": "WUNI11A", "name": "WUNI11A", "share_pct": 3.953172718018324, "qty": 5592.0}, {"custnmbr": "MAC220A", "name": "MAC220A", "share_pct": 3.571428571428571, "qty": 5052.0}, {"custnmbr": "LFORE2A", "name": "LFORE2A", "share_pct": 1.815405497115711, "qty": 2568.0}]}