{"sku": "F-12998", "dc": "LA", "series": [{"week_start": "2023-04-03", "on_hand_est": 12241.0, "reorder_point_mean": 96.0, "reorder_point_p90": 96.0, "run_rate_mean": 32.0, "run_rate_p90": 32.0, "alert_fired_mean": false, "alert_fired_p90": false, "fresh_stockout": false, "weeks_until_stockout": null}, {"week_start": "2023-05-01", "on_hand_est": 12241.0, "reorder_point_mean": 96.0, "reorder_point_p90": 96.0, "run_rate_mean": 32.0, "run_rate_p90": 32.0, "alert_fired_mean": false, "alert_fired_p90": false, "fresh_stockout": false, "weeks_until_stockout": null}, {"week_start": "2023-05-29", "on_hand_est": 12241.0, "reorder_point_mean": 96.0, "reorder_point_p90": 96.0, "run_rate_mean": 32.0, "run_rate_p90": 32.0, "alert_fired_mean": false, "alert_fired_p90": false, "fresh_stockout": false, "weeks_until_stockout": null}, {"week_start": "2023-06-26", "on_hand_est": 12241.0, "reorder_point_mean": 96.0, "reorder_point_p90": 96.0, "run_rate_mean": 32.0, "run_rate_p90": 32.0, "alert_fired_mean": false, "alert_fired_p90": false, "fresh_stockout": false, "weeks_until_stockout": null}, {"week_start": "2023-07-24", "on_hand_est": 12241.0, "reorder_point_mean": 96.0, "reorder_point_p90": 96.0, "run_rate_mean": 32.0, "run_rate_p90": 32.0, "alert_fired_mean": false, "alert_fired_p90": false, "fresh_stockout": false, "weeks_until_stockout": null}, {"week_start": "2023-08-21", "on_hand_est": 12241.0, "reorder_point_mean": 96.0, "reorder_point_p90": 96.0, "run_rate_mean": 32.0, "run_rate_p90": 32.0, "alert_fired_mean": false, "alert_fired_p90": false, "fresh_stockout": false, "weeks_until_stockout": null}, {"week_start": "2023-09-18", "on_hand_est": 12241.0, "reorder_point_mean": 123.42857142857143, "reorder_point_p90": 123.42857142857143, "run_rate_mean": 32.0, "run_rate_p90": 32.0, "alert_fired_mean": false, "alert_fired_p90": false, "fresh_stockout": false, "weeks_until_stockout": null}, {"week_start": "2023-10-16", "on_hand_est": 12002.0, "reorder_point_mean": 627.3748370944403, "reorder_point_p90": 1015.0160243634238, "run_rate_mean": 101.33333333333333, "run_rate_p90": 198.4, "alert_fired_mean": false, "alert_fired_p90": false, "fresh_stockout": false, "weeks_until_stockout": null}, {"week_start": "2023-11-13", "on_hand_est": 11651.0, "reorder_point_mean": 481.1977814380687, "reorder_point_p90": 1056.6366721295178, "run_rate_mean": 93.71428571428571, "run_rate_p90": 259.20000000000005, "alert_fired_mean": false, "alert_fired_p90": false, "fresh_stockout": false, "weeks_until_stockout": null}, {"week_start": "2023-12-11", "on_hand_est": 11459.0, "reorder_point_mean": 392.4899108389489, "reorder_point_p90": 965.0273588405621, "run_rate_mean": 77.0909090909091, "run_rate_p90": 240.0, "alert_fired_mean": false, "alert_fired_p90": false, "fresh_stockout": false, "weeks_until_stockout": null}, {"week_start": "2024-01-08", "on_hand_est": 11077.0, "reorder_point_mean": 354.542701477267, "reorder_point_p90": 713.8525950173298, "run_rate_mean": 75.73333333333333, "run_rate_p90": 195.19999999999996, "alert_fired_mean": false, "alert_fired_p90": false, "fresh_stockout": false, "weeks_until_stockout": null}, {"week_start": "2024-02-05", "on_hand_est": 10873.0, "reorder_point_mean": 340.1226539683171, "reorder_point_p90": 626.5067203330426, "run_rate_mean": 72.42105263157895, "run_rate_p90": 163.19999999999993, "alert_fired_mean": false, "alert_fired_p90": false, "fresh_stockout": false, "weeks_until_stockout": null}, {"week_start": "2024-03-04", "on_hand_est": 10635.0, "reorder_point_mean": 317.48165201931533, "reorder_point_p90": 527.4350801457833, "run_rate_mean": 70.95652173913044, "run_rate_p90": 140.8, "alert_fired_mean": false, "alert_fired_p90": false, "fresh_stockout": false, "weeks_until_stockout": null}, {"week_start": "2024-04-01", "on_hand_est": 10395.0, "reorder_point_mean": 336.8646272024747, "reorder_point_p90": 538.0288557637119, "run_rate_mean": 69.33333333333333, "run_rate_p90": 134.40000000000003, "alert_fired_mean": false, "alert_fired_p90": false, "fresh_stockout": false, "weeks_until_stockout": null}, {"week_start": "2024-04-29", "on_hand_est": 10187.0, "reorder_point_mean": 322.5982593892751, "reorder_point_p90": 511.23198615465066, "run_rate_mean": 67.09677419354838, "run_rate_p90": 128.0, "alert_fired_mean": false, "alert_fired_p90": false, "fresh_stockout": false, "weeks_until_stockout": null}, {"week_start": "2024-05-27", "on_hand_est": 10139.0, "reorder_point_mean": 280.2942564722933, "reorder_point_p90": 477.2025603611809, "run_rate_mean": 62.588235294117645, "run_rate_p90": 128.0, "alert_fired_mean": false, "alert_fired_p90": false, "fresh_stockout": false, "weeks_until_stockout": null}, {"week_start": "2024-06-24", "on_hand_est": 9963.0, "reorder_point_mean": 275.748127620421, "reorder_point_p90": 476.6452228669966, "run_rate_mean": 61.25714285714286, "run_rate_p90": 128.0, "alert_fired_mean": false, "alert_fired_p90": false, "fresh_stockout": false, "weeks_until_stockout": null}, {"week_start": "2024-07-22", "on_hand_est": 9965.0, "reorder_point_mean": 284.3641031059775, "reorder_point_p90": 497.1802003033977, "run_rate_mean": 61.25714285714286, "run_rate_p90": 128.0, "alert_fired_mean": false, "alert_fired_p90": false, "fresh_stockout": false, "weeks_until_stockout": null}, {"week_start": "2024-08-19", "on_hand_est": 9518.0, "reorder_point_mean": 339.21949978218584, "reorder_point_p90": 540.0618506628705, "run_rate_mean": 70.05405405405405, "run_rate_p90": 134.39999999999998, "alert_fired_mean": false, "alert_fired_p90": false, "fresh_stockout": false, "weeks_until_stockout": null}, {"week_start": "2024-09-16", "on_hand_est": 9392.0, "reorder_point_mean": 330.0561777745769, "reorder_point_p90": 524.1976185788287, "run_rate_mean": 68.0, "run_rate_p90": 129.60000000000002, "alert_fired_mean": false, "alert_fired_p90": false, "fresh_stockout": false, "weeks_until_stockout": null}, {"week_start": "2024-10-14", "on_hand_est": 7648.0, "reorder_point_mean": 727.3457806515337, "reorder_point_p90": 834.8240292246747, "run_rate_mean": 103.81395348837209, "run_rate_p90": 140.80000000000007, "alert_fired_mean": false, "alert_fired_p90": false, "fresh_stockout": false, "weeks_until_stockout": null}, {"week_start": "2024-11-11", "on_hand_est": 7649.0, "reorder_point_mean": 726.6011850191983, "reorder_point_p90": 833.4749263271235, "run_rate_mean": 103.81395348837209, "run_rate_p90": 140.80000000000007, "alert_fired_mean": false, "alert_fired_p90": false, "fresh_stockout": false, "weeks_until_stockout": null}, {"week_start": "2024-12-09", "on_hand_est": 7105.0, "reorder_point_mean": 714.0001310610576, "reorder_point_p90": 969.4735187493802, "run_rate_mean": 104.85106382978724, "run_rate_p90": 191.9999999999999, "alert_fired_mean": false, "alert_fired_p90": false, "fresh_stockout": false, "weeks_until_stockout": null}, {"week_start": "2025-01-06", "on_hand_est": 7073.0, "reorder_point_mean": 705.6078005594932, "reorder_point_p90": 941.7186196169627, "run_rate_mean": 103.33333333333333, "run_rate_p90": 184.00000000000034, "alert_fired_mean": false, "alert_fired_p90": false, "fresh_stockout": false, "weeks_until_stockout": null}, {"week_start": "2025-02-03", "on_hand_est": 7073.0, "reorder_point_mean": 705.6078005594932, "reorder_point_p90": 941.7186196169627, "run_rate_mean": 103.33333333333333, "run_rate_p90": 184.00000000000034, "alert_fired_mean": false, "alert_fired_p90": false, "fresh_stockout": false, "weeks_until_stockout": null}, {"week_start": "2025-03-03", "on_hand_est": 7073.0, "reorder_point_mean": 705.6078005594932, "reorder_point_p90": 941.7186196169627, "run_rate_mean": 103.33333333333333, "run_rate_p90": 184.00000000000034, "alert_fired_mean": false, "alert_fired_p90": false, "fresh_stockout": false, "weeks_until_stockout": null}, {"week_start": "2025-03-31", "on_hand_est": 6803.0, "reorder_point_mean": 701.3512692199931, "reorder_point_p90": 1104.9619912775115, "run_rate_mean": 107.10204081632654, "run_rate_p90": 246.4000000000001, "alert_fired_mean": false, "alert_fired_p90": false, "fresh_stockout": false, "weeks_until_stockout": null}, {"week_start": "2025-04-28", "on_hand_est": 6516.0, "reorder_point_mean": 665.7256674431139, "reorder_point_p90": 1001.1331763749191, "run_rate_mean": 104.45283018867924, "run_rate_p90": 224.00000000000034, "alert_fired_mean": false, "alert_fired_p90": false, "fresh_stockout": false, "weeks_until_stockout": null}, {"week_start": "2025-05-26", "on_hand_est": 6293.0, "reorder_point_mean": 670.0057998116349, "reorder_point_p90": 1035.1016817973505, "run_rate_mean": 106.66666666666667, "run_rate_p90": 235.20000000000005, "alert_fired_mean": false, "alert_fired_p90": false, "fresh_stockout": false, "weeks_until_stockout": null}, {"week_start": "2025-06-23", "on_hand_est": 6166.0, "reorder_point_mean": 643.2729497037802, "reorder_point_p90": 1002.9919388010187, "run_rate_mean": 101.51724137931035, "run_rate_p90": 228.80000000000007, "alert_fired_mean": false, "alert_fired_p90": false, "fresh_stockout": false, "weeks_until_stockout": null}, {"week_start": "2025-07-21", "on_hand_est": 6040.0, "reorder_point_mean": 627.963979651856, "reorder_point_p90": 983.4879958104682, "run_rate_mean": 98.88524590163935, "run_rate_p90": 224.0, "alert_fired_mean": false, "alert_fired_p90": false, "fresh_stockout": false, "weeks_until_stockout": null}, {"week_start": "2025-08-18", "on_hand_est": 5784.0, "reorder_point_mean": 611.1164012665855, "reorder_point_p90": 898.6503223971708, "run_rate_mean": 96.73846153846154, "run_rate_p90": 198.4000000000001, "alert_fired_mean": false, "alert_fired_p90": false, "fresh_stockout": false, "weeks_until_stockout": null}, {"week_start": "2025-09-15", "on_hand_est": 5656.0, "reorder_point_mean": 603.3112630968662, "reorder_point_p90": 856.7553516595443, "run_rate_mean": 95.76119402985074, "run_rate_p90": 185.5999999999999, "alert_fired_mean": false, "alert_fired_p90": false, "fresh_stockout": false, "weeks_until_stockout": null}, {"week_start": "2025-10-13", "on_hand_est": 5417.0, "reorder_point_mean": 603.8811452241458, "reorder_point_p90": 801.0646488872051, "run_rate_mean": 93.74647887323944, "run_rate_p90": 160.0, "alert_fired_mean": false, "alert_fired_p90": false, "fresh_stockout": false, "weeks_until_stockout": null}], "today": {"reorder_flag": true, "confidence": "high", "on_hand": 0.0, "available": 0.0, "reorder_point": 884.8419394104583, "run_rate_wk": 109.0752688172043, "lead_time_wk": 2.642857142857143, "lead_time_source": "po_history", "suggested_qty": 1328.0, "suggested_cases": 83.0, "weeks_of_cover": 0.0, "safety_stock": 596.5715861078469, "std_wk": 222.40358128563705, "n_clean_weeks": 93}, "metadata": {"sku_desc": "Ferrero Rocher 48's Flat Gift Box", "case_pack": 16.0, "vendor": "Ferrero USA", "country": "Poland"}}