{"sku": "T-31510", "dc": "SF", "series": [{"week_start": "2023-04-03", "on_hand_est": 2009173.0, "reorder_point_mean": 19350.50530311486, "reorder_point_p90": 33342.23542539848, "run_rate_mean": 3662.6923076923076, "run_rate_p90": 7275.2, "alert_fired_mean": false, "alert_fired_p90": false, "fresh_stockout": false, "weeks_until_stockout": null}, {"week_start": "2023-05-01", "on_hand_est": 1976378.0, "reorder_point_mean": 19216.875078239682, "reorder_point_p90": 31980.792625445272, "run_rate_mean": 3805.1176470588234, "run_rate_p90": 7135.6, "alert_fired_mean": false, "alert_fired_p90": false, "fresh_stockout": false, "weeks_until_stockout": null}, {"week_start": "2023-05-29", "on_hand_est": 1914016.0, "reorder_point_mean": 24508.60197837736, "reorder_point_p90": 43424.675523805316, "run_rate_mean": 4791.666666666667, "run_rate_p90": 9727.0, "alert_fired_mean": false, "alert_fired_p90": false, "fresh_stockout": false, "weeks_until_stockout": null}, {"week_start": "2023-06-26", "on_hand_est": 1872207.0, "reorder_point_mean": 23636.03266356096, "reorder_point_p90": 38753.468115320466, "run_rate_mean": 5261.36, "run_rate_p90": 9818.800000000001, "alert_fired_mean": false, "alert_fired_p90": false, "fresh_stockout": false, "weeks_until_stockout": null}, {"week_start": "2023-07-24", "on_hand_est": 1833373.0, "reorder_point_mean": 29289.710085308285, "reorder_point_p90": 47985.694650184625, "run_rate_mean": 5606.3448275862065, "run_rate_p90": 9909.6, "alert_fired_mean": false, "alert_fired_p90": false, "fresh_stockout": false, "weeks_until_stockout": null}, {"week_start": "2023-08-21", "on_hand_est": 1802871.0, "reorder_point_mean": 31003.12418333193, "reorder_point_p90": 54622.45839723601, "run_rate_mean": 5170.121212121212, "run_rate_p90": 9849.4, "alert_fired_mean": false, "alert_fired_p90": false, "fresh_stockout": false, "weeks_until_stockout": null}, {"week_start": "2023-09-18", "on_hand_est": 1752421.0, "reorder_point_mean": 36020.042146111125, "reorder_point_p90": 65219.5005228426, "run_rate_mean": 5751.783783783784, "run_rate_p90": 11297.599999999999, "alert_fired_mean": false, "alert_fired_p90": false, "fresh_stockout": false, "weeks_until_stockout": null}, {"week_start": "2023-10-16", "on_hand_est": 1710829.0, "reorder_point_mean": 33274.091588365285, "reorder_point_p90": 59003.57020173989, "run_rate_mean": 5737.585365853659, "run_rate_p90": 10980.0, "alert_fired_mean": false, "alert_fired_p90": false, "fresh_stockout": false, "weeks_until_stockout": null}, {"week_start": "2023-11-13", "on_hand_est": 1661125.0, "reorder_point_mean": 31408.62942230139, "reorder_point_p90": 54504.74103954583, "run_rate_mean": 5708.933333333333, "run_rate_p90": 10599.2, "alert_fired_mean": false, "alert_fired_p90": false, "fresh_stockout": false, "weeks_until_stockout": null}, {"week_start": "2023-12-11", "on_hand_est": 1609669.0, "reorder_point_mean": 32691.953344730766, "reorder_point_p90": 55330.78234897849, "run_rate_mean": 5641.081632653061, "run_rate_p90": 10218.400000000003, "alert_fired_mean": false, "alert_fired_p90": false, "fresh_stockout": false, "weeks_until_stockout": null}, {"week_start": "2024-01-08", "on_hand_est": 1562297.0, "reorder_point_mean": 34399.585990648964, "reorder_point_p90": 56527.94520367561, "run_rate_mean": 5695.566037735849, "run_rate_p90": 9998.400000000001, "alert_fired_mean": false, "alert_fired_p90": false, "fresh_stockout": false, "weeks_until_stockout": null}, {"week_start": "2024-02-05", "on_hand_est": 1509724.0, "reorder_point_mean": 37334.739319527434, "reorder_point_p90": 59404.71525631068, "run_rate_mean": 5885.859649122807, "run_rate_p90": 9939.199999999999, "alert_fired_mean": false, "alert_fired_p90": false, "fresh_stockout": false, "weeks_until_stockout": null}, {"week_start": "2024-03-04", "on_hand_est": 1462464.0, "reorder_point_mean": 37805.234300715645, "reorder_point_p90": 59864.309424624575, "run_rate_mean": 5984.295081967213, "run_rate_p90": 10028.0, "alert_fired_mean": false, "alert_fired_p90": false, "fresh_stockout": false, "weeks_until_stockout": null}, {"week_start": "2024-04-01", "on_hand_est": 1409840.0, "reorder_point_mean": 38819.80594544517, "reorder_point_p90": 63646.84603101316, "run_rate_mean": 6156.461538461538, "run_rate_p90": 10695.2, "alert_fired_mean": false, "alert_fired_p90": false, "fresh_stockout": false, "weeks_until_stockout": null}, {"week_start": "2024-04-29", "on_hand_est": 1348318.0, "reorder_point_mean": 37433.6242261936, "reorder_point_p90": 62328.79717134911, "run_rate_mean": 6305.68115942029, "run_rate_p90": 11090.800000000001, "alert_fired_mean": false, "alert_fired_p90": false, "fresh_stockout": false, "weeks_until_stockout": null}, {"week_start": "2024-05-27", "on_hand_est": 1301152.0, "reorder_point_mean": 39981.65241799516, "reorder_point_p90": 67563.87799739186, "run_rate_mean": 6387.2054794520545, "run_rate_p90": 11423.199999999999, "alert_fired_mean": false, "alert_fired_p90": false, "fresh_stockout": false, "weeks_until_stockout": null}, {"week_start": "2024-06-24", "on_hand_est": 1243484.0, "reorder_point_mean": 40757.3294889057, "reorder_point_p90": 69478.07652832047, "run_rate_mean": 6517.272727272727, "run_rate_p90": 11756.6, "alert_fired_mean": false, "alert_fired_p90": false, "fresh_stockout": false, "weeks_until_stockout": null}, {"week_start": "2024-07-22", "on_hand_est": 1220457.0, "reorder_point_mean": 37511.75803624997, "reorder_point_p90": 65074.78787849369, "run_rate_mean": 6377.2962962962965, "run_rate_p90": 11745.0, "alert_fired_mean": false, "alert_fired_p90": false, "fresh_stockout": false, "weeks_until_stockout": null}, {"week_start": "2024-08-19", "on_hand_est": 1170549.0, "reorder_point_mean": 39155.89593331485, "reorder_point_p90": 67935.20350926623, "run_rate_mean": 6320.482352941176, "run_rate_p90": 11660.600000000002, "alert_fired_mean": false, "alert_fired_p90": false, "fresh_stockout": false, "weeks_until_stockout": null}, {"week_start": "2024-09-16", "on_hand_est": 1129829.0, "reorder_point_mean": 40873.77089507947, "reorder_point_p90": 70575.42574176479, "run_rate_mean": 6301.6741573033705, "run_rate_p90": 11576.2, "alert_fired_mean": false, "alert_fired_p90": false, "fresh_stockout": false, "weeks_until_stockout": null}, {"week_start": "2024-10-14", "on_hand_est": 1076982.0, "reorder_point_mean": 39775.62672488698, "reorder_point_p90": 68863.98205430043, "run_rate_mean": 6351.537634408603, "run_rate_p90": 11702.8, "alert_fired_mean": false, "alert_fired_p90": false, "fresh_stockout": false, "weeks_until_stockout": null}, {"week_start": "2024-11-11", "on_hand_est": 1022215.0, "reorder_point_mean": 38618.541755790844, "reorder_point_p90": 65299.120237522846, "run_rate_mean": 6537.649484536082, "run_rate_p90": 11789.2, "alert_fired_mean": false, "alert_fired_p90": false, "fresh_stockout": false, "weeks_until_stockout": null}, {"week_start": "2024-12-09", "on_hand_est": 968683.0, "reorder_point_mean": 38388.05061742164, "reorder_point_p90": 65173.1406574849, "run_rate_mean": 6505.782178217822, "run_rate_p90": 11774.0, "alert_fired_mean": false, "alert_fired_p90": false, "fresh_stockout": false, "weeks_until_stockout": null}, {"week_start": "2025-01-06", "on_hand_est": 921370.0, "reorder_point_mean": 38191.63608860268, "reorder_point_p90": 65055.2430400462, "run_rate_mean": 6484.314285714286, "run_rate_p90": 11762.4, "alert_fired_mean": false, "alert_fired_p90": false, "fresh_stockout": false, "weeks_until_stockout": null}, {"week_start": "2025-02-03", "on_hand_est": 856128.0, "reorder_point_mean": 40042.8748009835, "reorder_point_p90": 67183.85909499264, "run_rate_mean": 6643.807339449541, "run_rate_p90": 11866.400000000001, "alert_fired_mean": false, "alert_fired_p90": false, "fresh_stockout": false, "weeks_until_stockout": null}, {"week_start": "2025-03-03", "on_hand_est": 776867.0, "reorder_point_mean": 41792.37061446972, "reorder_point_p90": 69203.57974347314, "run_rate_mean": 6724.3893805309735, "run_rate_p90": 11812.0, "alert_fired_mean": false, "alert_fired_p90": false, "fresh_stockout": false, "weeks_until_stockout": null}, {"week_start": "2025-03-31", "on_hand_est": 721908.0, "reorder_point_mean": 45624.66426834164, "reorder_point_p90": 77182.06970506732, "run_rate_mean": 6872.34188034188, "run_rate_p90": 12279.0, "alert_fired_mean": false, "alert_fired_p90": false, "fresh_stockout": false, "weeks_until_stockout": null}, {"week_start": "2025-04-28", "on_hand_est": 680686.0, "reorder_point_mean": 47585.81510915626, "reorder_point_p90": 80823.64503411792, "run_rate_mean": 6837.752066115702, "run_rate_p90": 12245.0, "alert_fired_mean": false, "alert_fired_p90": false, "fresh_stockout": false, "weeks_until_stockout": null}, {"week_start": "2025-05-26", "on_hand_est": 631285.0, "reorder_point_mean": 44431.3068405753, "reorder_point_p90": 75089.06127293513, "run_rate_mean": 6829.608, "run_rate_p90": 12180.600000000002, "alert_fired_mean": false, "alert_fired_p90": false, "fresh_stockout": false, "weeks_until_stockout": null}, {"week_start": "2025-06-23", "on_hand_est": 596828.0, "reorder_point_mean": 43605.851260769676, "reorder_point_p90": 73212.25056379751, "run_rate_mean": 6859.395348837209, "run_rate_p90": 12116.2, "alert_fired_mean": false, "alert_fired_p90": false, "fresh_stockout": false, "weeks_until_stockout": null}, {"week_start": "2025-07-21", "on_hand_est": 563725.0, "reorder_point_mean": 44554.81706120833, "reorder_point_p90": 75104.46211087523, "run_rate_mean": 6876.669172932331, "run_rate_p90": 12212.8, "alert_fired_mean": false, "alert_fired_p90": false, "fresh_stockout": false, "weeks_until_stockout": null}, {"week_start": "2025-08-18", "on_hand_est": 515640.0, "reorder_point_mean": 45926.65984561739, "reorder_point_p90": 76930.57525022865, "run_rate_mean": 6951.5474452554745, "run_rate_p90": 12279.0, "alert_fired_mean": false, "alert_fired_p90": false, "fresh_stockout": false, "weeks_until_stockout": null}, {"week_start": "2025-09-15", "on_hand_est": 472236.0, "reorder_point_mean": 44189.15772738744, "reorder_point_p90": 74516.16330374786, "run_rate_mean": 6877.574468085107, "run_rate_p90": 12245.0, "alert_fired_mean": false, "alert_fired_p90": false, "fresh_stockout": false, "weeks_until_stockout": null}, {"week_start": "2025-10-13", "on_hand_est": 434574.0, "reorder_point_mean": 43814.736691871134, "reorder_point_p90": 74157.02876748682, "run_rate_mean": 6806.068965517241, "run_rate_p90": 12180.599999999999, "alert_fired_mean": false, "alert_fired_p90": false, "fresh_stockout": false, "weeks_until_stockout": null}], "today": {"reorder_flag": false, "confidence": "high", "on_hand": 345054.0, "available": 318941.0, "reorder_point": 34319.28856247799, "run_rate_wk": 6696.458598726114, "lead_time_wk": 3.4285714285714284, "lead_time_source": "po_history", "suggested_qty": 0.0, "suggested_cases": 0.0, "weeks_of_cover": 47.628309097688295, "safety_stock": 11360.001938274172, "std_wk": 3718.2437825942225, "n_clean_weeks": 157}, "metadata": {"sku_desc": "Tiger Balm Ointment Ultra Strength 18g", "case_pack": 72.0, "vendor": "HPH", "country": "China"}}