{"sku": "T-31510", "dc": "SF", "series": [{"week_start": "2023-04-03", "actual": 2009173.0, "mean_followed": 1995210.0, "p90_followed": 1995210.0}, {"week_start": "2023-04-10", "actual": 2000110.0, "mean_followed": 1984541.0, "p90_followed": 1984541.0}, {"week_start": "2023-04-17", "actual": 1989441.0, "mean_followed": 1975478.0, "p90_followed": 1975478.0}, {"week_start": "2023-04-24", "actual": 1985178.0, "mean_followed": 1966678.0, "p90_followed": 1966678.0}, {"week_start": "2023-05-01", "actual": 1976378.0, "mean_followed": 1954448.0, "p90_followed": 1954448.0}, {"week_start": "2023-05-08", "actual": 1964148.0, "mean_followed": 1943864.0, "p90_followed": 1943864.0}, {"week_start": "2023-05-15", "actual": 1953564.0, "mean_followed": 1922611.0, "p90_followed": 1922611.0}, {"week_start": "2023-05-22", "actual": 1932311.0, "mean_followed": 1904316.0, "p90_followed": 1904316.0}, {"week_start": "2023-05-29", "actual": 1914016.0, "mean_followed": 1895436.0, "p90_followed": 1895436.0}, {"week_start": "2023-06-05", "actual": 1905136.0, "mean_followed": 1879108.0, "p90_followed": 1879108.0}, {"week_start": "2023-06-12", "actual": 1891808.0, "mean_followed": 1866749.0, "p90_followed": 1866749.0}, {"week_start": "2023-06-19", "actual": 1884449.0, "mean_followed": 1854507.0, "p90_followed": 1854507.0}, {"week_start": "2023-06-26", "actual": 1872207.0, "mean_followed": 1841619.0, "p90_followed": 1841619.0}, {"week_start": "2023-07-03", "actual": 1859319.0, "mean_followed": 1831597.0, "p90_followed": 1831597.0}, {"week_start": "2023-07-10", "actual": 1849297.0, "mean_followed": 1816367.0, "p90_followed": 1816367.0}, {"week_start": "2023-07-17", "actual": 1845867.0, "mean_followed": 1803873.0, "p90_followed": 1803873.0}, {"week_start": "2023-07-24", "actual": 1833373.0, "mean_followed": 1793604.0, "p90_followed": 1793604.0}, {"week_start": "2023-07-31", "actual": 1823104.0, "mean_followed": 1777941.0, "p90_followed": 1777941.0}, {"week_start": "2023-08-07", "actual": 1817441.0, "mean_followed": 1772312.0, "p90_followed": 1772312.0}, {"week_start": "2023-08-14", "actual": 1811812.0, "mean_followed": 1763371.0, "p90_followed": 1763371.0}, {"week_start": "2023-08-21", "actual": 1802871.0, "mean_followed": 1740111.0, "p90_followed": 1740111.0}, {"week_start": "2023-08-28", "actual": 1779611.0, "mean_followed": 1718536.0, "p90_followed": 1718536.0}, {"week_start": "2023-09-04", "actual": 1758036.0, "mean_followed": 1707556.0, "p90_followed": 1707556.0}, {"week_start": "2023-09-11", "actual": 1747056.0, "mean_followed": 1694421.0, "p90_followed": 1694421.0}, {"week_start": "2023-09-18", "actual": 1752421.0, "mean_followed": 1680951.0, "p90_followed": 1680951.0}, {"week_start": "2023-09-25", "actual": 1738951.0, "mean_followed": 1665747.0, "p90_followed": 1665747.0}, {"week_start": "2023-10-02", "actual": 1733747.0, "mean_followed": 1653413.0, "p90_followed": 1653413.0}, {"week_start": "2023-10-09", "actual": 1721413.0, "mean_followed": 1642829.0, "p90_followed": 1642829.0}, {"week_start": "2023-10-16", "actual": 1710829.0, "mean_followed": 1628107.0, "p90_followed": 1628107.0}, {"week_start": "2023-10-23", "actual": 1699607.0, "mean_followed": 1619370.0, "p90_followed": 1619370.0}, {"week_start": "2023-10-30", "actual": 1690870.0, "mean_followed": 1605117.0, "p90_followed": 1605117.0}, {"week_start": "2023-11-06", "actual": 1676617.0, "mean_followed": 1589625.0, "p90_followed": 1589625.0}, {"week_start": "2023-11-13", "actual": 1661125.0, "mean_followed": 1575030.0, "p90_followed": 1575030.0}, {"week_start": "2023-11-20", "actual": 1646530.0, "mean_followed": 1556509.0, "p90_followed": 1556509.0}, {"week_start": "2023-11-27", "actual": 1628009.0, "mean_followed": 1546479.0, "p90_followed": 1546479.0}, {"week_start": "2023-12-04", "actual": 1621979.0, "mean_followed": 1534169.0, "p90_followed": 1534169.0}, {"week_start": "2023-12-11", "actual": 1609669.0, "mean_followed": 1520561.0, "p90_followed": 1520561.0}, {"week_start": "2023-12-18", "actual": 1596061.0, "mean_followed": 1507493.0, "p90_followed": 1507493.0}, {"week_start": "2023-12-25", "actual": 1582993.0, "mean_followed": 1492109.0, "p90_followed": 1492109.0}, {"week_start": "2024-01-01", "actual": 1571609.0, "mean_followed": 1482797.0, "p90_followed": 1482797.0}, {"week_start": "2024-01-08", "actual": 1562297.0, "mean_followed": 1471036.0, "p90_followed": 1471036.0}, {"week_start": "2024-01-15", "actual": 1550536.0, "mean_followed": 1457642.0, "p90_followed": 1457642.0}, {"week_start": "2024-01-22", "actual": 1537142.0, "mean_followed": 1440997.0, "p90_followed": 1440997.0}, {"week_start": "2024-01-29", "actual": 1520497.0, "mean_followed": 1429224.0, "p90_followed": 1429224.0}, {"week_start": "2024-02-05", "actual": 1509724.0, "mean_followed": 1412511.0, "p90_followed": 1412511.0}, {"week_start": "2024-02-12", "actual": 1493011.0, "mean_followed": 1401501.0, "p90_followed": 1401501.0}, {"week_start": "2024-02-19", "actual": 1482001.0, "mean_followed": 1392339.0, "p90_followed": 1392339.0}, {"week_start": "2024-02-26", "actual": 1472839.0, "mean_followed": 1381964.0, "p90_followed": 1381964.0}, {"week_start": "2024-03-04", "actual": 1462464.0, "mean_followed": 1371996.0, "p90_followed": 1371996.0}, {"week_start": "2024-03-11", "actual": 1452496.0, "mean_followed": 1354707.0, "p90_followed": 1354707.0}, {"week_start": "2024-03-18", "actual": 1435207.0, "mean_followed": 1338823.0, "p90_followed": 1338823.0}, {"week_start": "2024-03-25", "actual": 1419323.0, "mean_followed": 1329340.0, "p90_followed": 1329340.0}, {"week_start": "2024-04-01", "actual": 1409840.0, "mean_followed": 1314767.0, "p90_followed": 1314767.0}, {"week_start": "2024-04-08", "actual": 1395267.0, "mean_followed": 1299006.0, "p90_followed": 1299006.0}, {"week_start": "2024-04-15", "actual": 1379506.0, "mean_followed": 1282480.0, "p90_followed": 1282480.0}, {"week_start": "2024-04-22", "actual": 1366980.0, "mean_followed": 1263818.0, "p90_followed": 1263818.0}, {"week_start": "2024-04-29", "actual": 1348318.0, "mean_followed": 1246016.0, "p90_followed": 1246016.0}, {"week_start": "2024-05-06", "actual": 1330516.0, "mean_followed": 1232842.0, "p90_followed": 1232842.0}, {"week_start": "2024-05-13", "actual": 1318342.0, "mean_followed": 1224052.0, "p90_followed": 1224052.0}, {"week_start": "2024-05-20", "actual": 1309552.0, "mean_followed": 1215652.0, "p90_followed": 1215652.0}, {"week_start": "2024-05-27", "actual": 1301152.0, "mean_followed": 1205030.0, "p90_followed": 1205030.0}, {"week_start": "2024-06-03", "actual": 1290530.0, "mean_followed": 1196448.0, "p90_followed": 1196448.0}, {"week_start": "2024-06-10", "actual": 1281948.0, "mean_followed": 1174332.0, "p90_followed": 1174332.0}, {"week_start": "2024-06-17", "actual": 1259832.0, "mean_followed": 1157984.0, "p90_followed": 1157984.0}, {"week_start": "2024-06-24", "actual": 1243484.0, "mean_followed": 1151583.0, "p90_followed": 1151583.0}, {"week_start": "2024-07-01", "actual": 1237083.0, "mean_followed": 1143043.0, "p90_followed": 1143043.0}, {"week_start": "2024-07-08", "actual": 1228543.0, "mean_followed": 1136268.0, "p90_followed": 1136268.0}, {"week_start": "2024-07-15", "actual": 1221768.0, "mean_followed": 1126837.0, "p90_followed": 1126837.0}, {"week_start": "2024-07-22", "actual": 1220457.0, "mean_followed": 1109891.0, "p90_followed": 1109891.0}, {"week_start": "2024-07-29", "actual": 1203511.0, "mean_followed": 1100986.0, "p90_followed": 1100986.0}, {"week_start": "2024-08-05", "actual": 1195906.0, "mean_followed": 1084951.0, "p90_followed": 1084951.0}, {"week_start": "2024-08-12", "actual": 1179871.0, "mean_followed": 1075629.0, "p90_followed": 1075629.0}, {"week_start": "2024-08-19", "actual": 1170549.0, "mean_followed": 1063089.0, "p90_followed": 1063089.0}, {"week_start": "2024-08-26", "actual": 1158009.0, "mean_followed": 1049482.0, "p90_followed": 1049482.0}, {"week_start": "2024-09-02", "actual": 1144402.0, "mean_followed": 1039834.0, "p90_followed": 1039834.0}, {"week_start": "2024-09-09", "actual": 1134754.0, "mean_followed": 1027109.0, "p90_followed": 1027109.0}, {"week_start": "2024-09-16", "actual": 1129829.0, "mean_followed": 1014549.0, "p90_followed": 1014549.0}, {"week_start": "2024-09-23", "actual": 1117269.0, "mean_followed": 1000242.0, "p90_followed": 1000242.0}, {"week_start": "2024-09-30", "actual": 1102962.0, "mean_followed": 981209.0, "p90_followed": 981209.0}, {"week_start": "2024-10-07", "actual": 1087429.0, "mean_followed": 970762.0, "p90_followed": 970762.0}, {"week_start": "2024-10-14", "actual": 1076982.0, "mean_followed": 948481.0, "p90_followed": 948481.0}, {"week_start": "2024-10-21", "actual": 1058201.0, "mean_followed": 935980.0, "p90_followed": 935980.0}, {"week_start": "2024-10-28", "actual": 1051700.0, "mean_followed": 916983.0, "p90_followed": 916983.0}, {"week_start": "2024-11-04", "actual": 1032703.0, "mean_followed": 906495.0, "p90_followed": 906495.0}, {"week_start": "2024-11-11", "actual": 1022215.0, "mean_followed": 894507.0, "p90_followed": 894507.0}, {"week_start": "2024-11-18", "actual": 1010227.0, "mean_followed": 879741.0, "p90_followed": 879741.0}, {"week_start": "2024-11-25", "actual": 995461.0, "mean_followed": 867970.0, "p90_followed": 867970.0}, {"week_start": "2024-12-02", "actual": 983690.0, "mean_followed": 852963.0, "p90_followed": 852963.0}, {"week_start": "2024-12-09", "actual": 968683.0, "mean_followed": 841236.0, "p90_followed": 841236.0}, {"week_start": "2024-12-16", "actual": 956956.0, "mean_followed": 833563.0, "p90_followed": 833563.0}, {"week_start": "2024-12-23", "actual": 949283.0, "mean_followed": 817163.0, "p90_followed": 817163.0}, {"week_start": "2024-12-30", "actual": 932883.0, "mean_followed": 805650.0, "p90_followed": 805650.0}, {"week_start": "2025-01-06", "actual": 921370.0, "mean_followed": 786421.0, "p90_followed": 786421.0}, {"week_start": "2025-01-13", "actual": 906141.0, "mean_followed": 771640.0, "p90_followed": 771640.0}, {"week_start": "2025-01-20", "actual": 891360.0, "mean_followed": 754756.0, "p90_followed": 754756.0}, {"week_start": "2025-01-27", "actual": 874476.0, "mean_followed": 736408.0, "p90_followed": 736408.0}, {"week_start": "2025-02-03", "actual": 856128.0, "mean_followed": 707149.0, "p90_followed": 707149.0}, {"week_start": "2025-02-10", "actual": 829369.0, "mean_followed": 690618.0, "p90_followed": 690618.0}, {"week_start": "2025-02-17", "actual": 812838.0, "mean_followed": 673420.0, "p90_followed": 673420.0}, {"week_start": "2025-02-24", "actual": 795640.0, "mean_followed": 654647.0, "p90_followed": 654647.0}, {"week_start": "2025-03-03", "actual": 776867.0, "mean_followed": 638422.0, "p90_followed": 638422.0}, {"week_start": "2025-03-10", "actual": 760642.0, "mean_followed": 616504.0, "p90_followed": 616504.0}, {"week_start": "2025-03-17", "actual": 738724.0, "mean_followed": 595252.0, "p90_followed": 595252.0}, {"week_start": "2025-03-24", "actual": 728472.0, "mean_followed": 588688.0, "p90_followed": 588688.0}, {"week_start": "2025-03-31", "actual": 721908.0, "mean_followed": 574646.0, "p90_followed": 574646.0}, {"week_start": "2025-04-07", "actual": 713866.0, "mean_followed": 560755.0, "p90_followed": 560755.0}, {"week_start": "2025-04-14", "actual": 699975.0, "mean_followed": 550109.0, "p90_followed": 550109.0}, {"week_start": "2025-04-21", "actual": 689329.0, "mean_followed": 541466.0, "p90_followed": 541466.0}, {"week_start": "2025-04-28", "actual": 680686.0, "mean_followed": 522870.0, "p90_followed": 522870.0}, {"week_start": "2025-05-05", "actual": 662090.0, "mean_followed": 514372.0, "p90_followed": 514372.0}, {"week_start": "2025-05-12", "actual": 656092.0, "mean_followed": 496403.0, "p90_followed": 496403.0}, {"week_start": "2025-05-19", "actual": 638123.0, "mean_followed": 484965.0, "p90_followed": 484965.0}, {"week_start": "2025-05-26", "actual": 631285.0, "mean_followed": 473876.0, "p90_followed": 473876.0}, {"week_start": "2025-06-02", "actual": 620196.0, "mean_followed": 465888.0, "p90_followed": 465888.0}, {"week_start": "2025-06-09", "actual": 612208.0, "mean_followed": 454227.0, "p90_followed": 454227.0}, {"week_start": "2025-06-16", "actual": 600547.0, "mean_followed": 443508.0, "p90_followed": 443508.0}, {"week_start": "2025-06-23", "actual": 596828.0, "mean_followed": 436474.0, "p90_followed": 436474.0}, {"week_start": "2025-06-30", "actual": 589794.0, "mean_followed": 426707.0, "p90_followed": 426707.0}, {"week_start": "2025-07-07", "actual": 580027.0, "mean_followed": 411178.0, "p90_followed": 411178.0}, {"week_start": "2025-07-14", "actual": 571498.0, "mean_followed": 403405.0, "p90_followed": 403405.0}, {"week_start": "2025-07-21", "actual": 563725.0, "mean_followed": 384728.0, "p90_followed": 384728.0}, {"week_start": "2025-07-28", "actual": 545048.0, "mean_followed": 371591.0, "p90_followed": 371591.0}, {"week_start": "2025-08-04", "actual": 543911.0, "mean_followed": 354613.0, "p90_followed": 354613.0}, {"week_start": "2025-08-11", "actual": 526933.0, "mean_followed": 343320.0, "p90_followed": 343320.0}, {"week_start": "2025-08-18", "actual": 515640.0, "mean_followed": 337395.0, "p90_followed": 337395.0}, {"week_start": "2025-08-25", "actual": 509715.0, "mean_followed": 313416.0, "p90_followed": 313416.0}, {"week_start": "2025-09-01", "actual": 490236.0, "mean_followed": 309024.0, "p90_followed": 309024.0}, {"week_start": "2025-09-08", "actual": 485844.0, "mean_followed": 295416.0, "p90_followed": 295416.0}, {"week_start": "2025-09-15", "actual": 472236.0, "mean_followed": 286416.0, "p90_followed": 286416.0}, {"week_start": "2025-09-22", "actual": 463236.0, "mean_followed": 277124.0, "p90_followed": 277124.0}, {"week_start": "2025-09-29", "actual": 453944.0, "mean_followed": 262434.0, "p90_followed": 262434.0}, {"week_start": "2025-10-06", "actual": 439254.0, "mean_followed": 257754.0, "p90_followed": 257754.0}, {"week_start": "2025-10-13", "actual": 434574.0, "mean_followed": 251778.0, "p90_followed": 251778.0}, {"week_start": "2025-10-20", "actual": 428598.0, "mean_followed": 244362.0, "p90_followed": 244362.0}, {"week_start": "2025-10-27", "actual": 421182.0, "mean_followed": 235914.0, "p90_followed": 235914.0}, {"week_start": "2025-11-03", "actual": 412734.0, "mean_followed": 229218.0, "p90_followed": 229218.0}, {"week_start": "2025-11-10", "actual": 406038.0, "mean_followed": 224106.0, "p90_followed": 224106.0}, {"week_start": "2025-11-17", "actual": 400926.0, "mean_followed": 213938.0, "p90_followed": 213938.0}, {"week_start": "2025-11-24", "actual": 390758.0, "mean_followed": 205345.0, "p90_followed": 205345.0}, {"week_start": "2025-12-01", "actual": 382165.0, "mean_followed": 201340.0, "p90_followed": 201340.0}, {"week_start": "2025-12-08", "actual": 378160.0, "mean_followed": 197440.0, "p90_followed": 197440.0}, {"week_start": "2025-12-15", "actual": 374260.0, "mean_followed": 189140.0, "p90_followed": 189140.0}, {"week_start": "2025-12-22", "actual": 365960.0, "mean_followed": 175808.0, "p90_followed": 175808.0}, {"week_start": "2025-12-29", "actual": 352628.0, "mean_followed": 168234.0, "p90_followed": 168234.0}, {"week_start": "2026-01-05", "actual": 345054.0, "mean_followed": 168234.0, "p90_followed": 168234.0}, {"week_start": "2026-01-12", "actual": 345054.0, "mean_followed": 168234.0, "p90_followed": 168234.0}, {"week_start": "2026-01-19", "actual": 345054.0, "mean_followed": 168234.0, "p90_followed": 168234.0}, {"week_start": "2026-01-26", "actual": 345054.0, "mean_followed": 168234.0, "p90_followed": 168234.0}, {"week_start": "2026-02-02", "actual": 345054.0, "mean_followed": 168234.0, "p90_followed": 168234.0}, {"week_start": "2026-02-09", "actual": 345054.0, "mean_followed": 168234.0, "p90_followed": 168234.0}, {"week_start": "2026-02-16", "actual": 345054.0, "mean_followed": 168234.0, "p90_followed": 168234.0}, {"week_start": "2026-02-23", "actual": 345054.0, "mean_followed": 168234.0, "p90_followed": 168234.0}, {"week_start": "2026-03-02", "actual": 345054.0, "mean_followed": 168234.0, "p90_followed": 168234.0}, {"week_start": "2026-03-09", "actual": 345054.0, "mean_followed": 168234.0, "p90_followed": 168234.0}, {"week_start": "2026-03-16", "actual": 345054.0, "mean_followed": 168234.0, "p90_followed": 168234.0}, {"week_start": "2026-03-23", "actual": 345054.0, "mean_followed": 168234.0, "p90_followed": 168234.0}, {"week_start": "2026-03-30", "actual": 345054.0, "mean_followed": 168234.0, "p90_followed": 168234.0}, {"week_start": "2026-04-06", "actual": 345054.0, "mean_followed": 168234.0, "p90_followed": 168234.0}, {"week_start": "2026-04-13", "actual": 345054.0, "mean_followed": 168234.0, "p90_followed": 168234.0}, {"week_start": "2026-04-20", "actual": 345054.0, "mean_followed": 168234.0, "p90_followed": 168234.0}], "simulated_pos": [], "trough_delta": {"actual": 345054.0, "mean": 168234.0, "p90": 168234.0}, "narrative": null}